{
  "original_vocab_size": 30522,
  "final_vocab_size": 35533,
  "special_tokens": [
    "[TISSUE]",
    "[SPATIAL]",
    "[CANCER]",
    "[IS_BORDER]",
    "[NOT_BORDER]",
    "[GENE]",
    "[REACT]",
    "[NEIGHBOR]",
    "[MITO_HIGH]",
    "[MITO_MED]",
    "[MITO_LOW]"
  ],
  "gene_tokens_len": 5000,
  "gene_tokens": [
    "gene_PLEKHN1",
    "gene_PERM1",
    "gene_ISG15",
    "gene_AGRN",
    "gene_RNF223",
    "gene_TTLL10",
    "gene_SDF4",
    "gene_B3GALT6",
    "gene_SCNN1D",
    "gene_TAS1R3",
    "gene_MXRA8",
    "gene_ANKRD65",
    "gene_VWA1",
    "gene_FNDC10",
    "gene_TMEM52",
    "gene_FAAP20",
    "gene_PEX10",
    "gene_HES5",
    "gene_TNFRSF14",
    "gene_CCDC27",
    "gene_SMIM1",
    "gene_CHD5",
    "gene_HES2",
    "gene_ESPN",
    "gene_VAMP3",
    "gene_UTS2",
    "gene_CA6",
    "gene_SLC2A7",
    "gene_SPSB1",
    "gene_SLC25A33",
    "gene_NMNAT1",
    "gene_MASP2",
    "gene_ANGPTL7",
    "gene_UBIAD1",
    "gene_C1orf167",
    "gene_NPPB",
    "gene_PLOD1",
    "gene_TNFRSF1B",
    "gene_VPS13D",
    "gene_PRAMEF1",
    "gene_PRAMEF11",
    "gene_PRAMEF2",
    "gene_PRAMEF4",
    "gene_PRAMEF10",
    "gene_PRAMEF6",
    "gene_PRAMEF27",
    "gene_PRAMEF18",
    "gene_PRAMEF8",
    "gene_PRAMEF33",
    "gene_PRAMEF15",
    "gene_PRAMEF14",
    "gene_PRAMEF19",
    "gene_PRAMEF20",
    "gene_PDPN",
    "gene_TMEM51",
    "gene_CELA2B",
    "gene_DDI2",
    "gene_TMEM82",
    "gene_CLCNKB",
    "gene_FAM131C",
    "gene_SZRD1",
    "gene_SPATA21",
    "gene_PADI2",
    "gene_PADI3",
    "gene_PADI4",
    "gene_PADI6",
    "gene_RCC2",
    "gene_KLHDC7A",
    "gene_PAX7",
    "gene_TAS1R2",
    "gene_RNF186",
    "gene_PLA2G2E",
    "gene_PLA2G2A",
    "gene_PLA2G2D",
    "gene_VWA5B1",
    "gene_MUL1",
    "gene_ECE1",
    "gene_HSPG2",
    "gene_CELA3A",
    "gene_C1QB",
    "gene_LACTBL1",
    "gene_TEX46",
    "gene_TCEA3",
    "gene_ID3",
    "gene_CNR2",
    "gene_IL22RA1",
    "gene_MTFR1L",
    "gene_EXTL1",
    "gene_SLC30A2",
    "gene_TRIM63",
    "gene_FAM110D",
    "gene_CATSPER4",
    "gene_CRYBG2",
    "gene_ZNF683",
    "gene_LIN28A",
    "gene_GPN2",
    "gene_NR0B2",
    "gene_KDF1",
    "gene_TENT5B",
    "gene_FGR",
    "gene_THEMIS2",
    "gene_RPA2",
    "gene_EYA3",
    "gene_SESN2",
    "gene_MED18",
    "gene_GMEB1",
    "gene_FABP3",
    "gene_TINAGL1",
    "gene_COL16A1",
    "gene_SPOCD1",
    "gene_DCDC2B",
    "gene_ZBTB8A",
    "gene_YARS",
    "gene_HPCA",
    "gene_PHC2",
    "gene_HMGB4",
    "gene_GJB4",
    "gene_GJB3",
    "gene_NCDN",
    "gene_EVA1B",
    "gene_EPHA10",
    "gene_INPP5B",
    "gene_POU3F1",
    "gene_GJA9",
    "gene_HPCAL4",
    "gene_OXCT2",
    "gene_CITED4",
    "gene_SLFNL1",
    "gene_EDN2",
    "gene_GUCA2B",
    "gene_GUCA2A",
    "gene_PPCS",
    "gene_CCDC30",
    "gene_PPIH",
    "gene_CLDN19",
    "gene_TMEM269",
    "gene_ZNF691",
    "gene_SLC2A1",
    "gene_EBNA1BP2",
    "gene_TMEM125",
    "gene_C1orf210",
    "gene_MPL",
    "gene_ELOVL1",
    "gene_ARTN",
    "gene_DPH2",
    "gene_CCDC24",
    "gene_SLC6A9",
    "gene_KLF18",
    "gene_TMEM53",
    "gene_BEST4",
    "gene_TCTEX1D4",
    "gene_EIF2B3",
    "gene_HPDL",
    "gene_TMEM69",
    "gene_P3R3URF",
    "gene_TMEM275",
    "gene_KNCN",
    "gene_TEX38",
    "gene_CYP4B1",
    "gene_CYP4Z1",
    "gene_FOXE3",
    "gene_FOXD2",
    "gene_SLC5A9",
    "gene_SPATA6",
    "gene_CDKN2C",
    "gene_C1orf185",
    "gene_KTI12",
    "gene_SHISAL2A",
    "gene_ZYG11A",
    "gene_PODN",
    "gene_SLC1A7",
    "gene_DIO1",
    "gene_LDLRAD1",
    "gene_CDCP2",
    "gene_TTC22",
    "gene_LEXM",
    "gene_BSND",
    "gene_TACSTD2",
    "gene_L1TD1",
    "gene_ANGPTL3",
    "gene_ALG6",
    "gene_AK4",
    "gene_LEPR",
    "gene_C1orf141",
    "gene_IL23R",
    "gene_SERBP1",
    "gene_GADD45A",
    "gene_DEPDC1",
    "gene_PTGER3",
    "gene_TYW3",
    "gene_AK5",
    "gene_AC118549.1",
    "gene_MIGA1",
    "gene_ADGRL4",
    "gene_LPAR3",
    "gene_DDAH1",
    "gene_CCN1",
    "gene_CLCA1",
    "gene_CLCA4",
    "gene_RBMXL1",
    "gene_GBP3",
    "gene_GBP1",
    "gene_GBP2",
    "gene_LRRC8B",
    "gene_LRRC8D",
    "gene_BARHL2",
    "gene_BRDT",
    "gene_GFI1",
    "gene_DIPK1A",
    "gene_BCAR3",
    "gene_ABCA4",
    "gene_ALG14",
    "gene_RTCA",
    "gene_CDC14A",
    "gene_GPR88",
    "gene_VCAM1",
    "gene_DPH5",
    "gene_S1PR1",
    "gene_COL11A1",
    "gene_AMY2A",
    "gene_PRMT6",
    "gene_SLC25A24",
    "gene_FNDC7",
    "gene_WDR47",
    "gene_GNAT2",
    "gene_CSF1",
    "gene_UBL4B",
    "gene_PROK1",
    "gene_KCNA10",
    "gene_CHI3L2",
    "gene_TAFA3",
    "gene_SLC16A1",
    "gene_BCL2L15",
    "gene_TSHB",
    "gene_MAB21L3",
    "gene_CD2",
    "gene_VTCN1",
    "gene_HAO2",
    "gene_PHGDH",
    "gene_HMGCS2",
    "gene_REG4",
    "gene_ADAM30",
    "gene_PPIAL4A",
    "gene_NBPF20",
    "gene_POLR3C",
    "gene_RBM8A",
    "gene_ANKRD34A",
    "gene_TXNIP",
    "gene_HJV",
    "gene_GJA5",
    "gene_GJA8",
    "gene_NBPF11",
    "gene_PPIAL4G",
    "gene_HIST2H2BE",
    "gene_BOLA1",
    "gene_SV2A",
    "gene_ANP32E",
    "gene_APH1A",
    "gene_PRPF3",
    "gene_RPRD2",
    "gene_MCL1",
    "gene_HORMAD1",
    "gene_CTSS",
    "gene_CTSK",
    "gene_CTXND2",
    "gene_C1orf56",
    "gene_MLLT11",
    "gene_SNX27",
    "gene_CELF3",
    "gene_LINGO4",
    "gene_RORC",
    "gene_THEM4",
    "gene_S100A10",
    "gene_S100A11",
    "gene_TCHHL1",
    "gene_TCHH",
    "gene_HRNR",
    "gene_FLG",
    "gene_FLG2",
    "gene_CRNN",
    "gene_LCE5A",
    "gene_CRCT1",
    "gene_LCE3D",
    "gene_LCE3C",
    "gene_LCE3A",
    "gene_LCE2D",
    "gene_LCE2A",
    "gene_LCE4A",
    "gene_C1orf68",
    "gene_KPRP",
    "gene_LCE1C",
    "gene_LCE1B",
    "gene_LCE1A",
    "gene_LCE6A",
    "gene_AL162596.1",
    "gene_IVL",
    "gene_SPRR5",
    "gene_SPRR4",
    "gene_SPRR3",
    "gene_SPRR1B",
    "gene_SPRR2D",
    "gene_SPRR2A",
    "gene_SPRR2E",
    "gene_SPRR2F",
    "gene_SPRR2G",
    "gene_LELP1",
    "gene_PRR9",
    "gene_LOR",
    "gene_PGLYRP4",
    "gene_S100A9",
    "gene_S100A12",
    "gene_S100A8",
    "gene_S100A7A",
    "gene_S100A7L2",
    "gene_S100A4",
    "gene_S100A3",
    "gene_S100A14",
    "gene_SLC27A3",
    "gene_SLC39A1",
    "gene_RAB13",
    "gene_NUP210L",
    "gene_AQP10",
    "gene_TDRD10",
    "gene_CKS1B",
    "gene_LENEP",
    "gene_EFNA1",
    "gene_DPM3",
    "gene_TRIM46",
    "gene_MUC1",
    "gene_MTX1",
    "gene_PKLR",
    "gene_MSTO1",
    "gene_UBQLN4",
    "gene_RAB25",
    "gene_MEX3A",
    "gene_LMNA",
    "gene_PAQR6",
    "gene_VHLL",
    "gene_TSACC",
    "gene_RHBG",
    "gene_TTC24",
    "gene_GPATCH4",
    "gene_HAPLN2",
    "gene_NES",
    "gene_RRNAD1",
    "gene_HDGF",
    "gene_SH2D2A",
    "gene_NTRK1",
    "gene_INSRR",
    "gene_LRRC71",
    "gene_FCRL5",
    "gene_FCRL4",
    "gene_FCRL2",
    "gene_FCRL1",
    "gene_CD5L",
    "gene_CD1D",
    "gene_CD1E",
    "gene_OR10K2",
    "gene_OR10K1",
    "gene_OR10R2",
    "gene_OR6Y1",
    "gene_OR6P1",
    "gene_OR10X1",
    "gene_OR6K2",
    "gene_OR6N1",
    "gene_OR6K6",
    "gene_OR6N2",
    "gene_PYHIN1",
    "gene_ACKR1",
    "gene_FCER1A",
    "gene_OR10J1",
    "gene_OR10J5",
    "gene_APCS",
    "gene_CRP",
    "gene_DUSP23",
    "gene_IGSF9",
    "gene_SLAMF9",
    "gene_ATP1A2",
    "gene_NHLH1",
    "gene_CD84",
    "gene_SLAMF1",
    "gene_CD48",
    "gene_SLAMF7",
    "gene_ITLN1",
    "gene_ITLN2",
    "gene_NECTIN4",
    "gene_KLHDC9",
    "gene_ADAMTS4",
    "gene_FCER1G",
    "gene_APOA2",
    "gene_NR1I3",
    "gene_FCGR2A",
    "gene_HSPA6",
    "gene_FCGR3A",
    "gene_FCRLB",
    "gene_SPATA46",
    "gene_SH2D1B",
    "gene_UAP1",
    "gene_RGS4",
    "gene_RGS5",
    "gene_LMX1A",
    "gene_LRRC52",
    "gene_GPA33",
    "gene_DUSP27",
    "gene_RCSD1",
    "gene_ADCY10",
    "gene_XCL1",
    "gene_DPT",
    "gene_SELP",
    "gene_C1orf112",
    "gene_SELL",
    "gene_METTL18",
    "gene_METTL11B",
    "gene_PRRX1",
    "gene_MROH9",
    "gene_FMO1",
    "gene_FMO4",
    "gene_MYOCOS",
    "gene_FASLG",
    "gene_TNN",
    "gene_CLEC20A",
    "gene_TEX35",
    "gene_FAM163A",
    "gene_LHX4",
    "gene_IER5",
    "gene_TEDDM1",
    "gene_RGSL1",
    "gene_RNASEL",
    "gene_LAMC1",
    "gene_LAMC2",
    "gene_SMG7",
    "gene_NCF2",
    "gene_APOBEC4",
    "gene_PTGS2",
    "gene_PLA2G4A",
    "gene_RGS1",
    "gene_RGS13",
    "gene_CFHR4",
    "gene_F13B",
    "gene_C1orf53",
    "gene_LHX9",
    "gene_ATP6V1G3",
    "gene_GPR25",
    "gene_CACNA1S",
    "gene_ASCL5",
    "gene_IGFN1",
    "gene_PKP1",
    "gene_LAD1",
    "gene_TNNI1",
    "gene_PHLDA3",
    "gene_LMOD1",
    "gene_PTPN7",
    "gene_MYOG",
    "gene_CHI3L1",
    "gene_BTG2",
    "gene_PRELP",
    "gene_LAX1",
    "gene_REN",
    "gene_KISS1",
    "gene_CNTN2",
    "gene_KLHDC8A",
    "gene_LEMD1",
    "gene_BLACAT1",
    "gene_CDK18",
    "gene_SLC26A9",
    "gene_CTSE",
    "gene_RHEX",
    "gene_AVPR1B",
    "gene_IKBKE",
    "gene_MAPKAPK2",
    "gene_IL19",
    "gene_IL20",
    "gene_FCAMR",
    "gene_C1orf116",
    "gene_YOD1",
    "gene_C4BPB",
    "gene_C4BPA",
    "gene_CR1",
    "gene_CR1L",
    "gene_CD34",
    "gene_G0S2",
    "gene_DTL",
    "gene_ATF3",
    "gene_FAM71A",
    "gene_BATF3",
    "gene_SPATA45",
    "gene_VASH2",
    "gene_CENPF",
    "gene_BPNT1",
    "gene_HLX",
    "gene_TLR5",
    "gene_CCDC185",
    "gene_DEGS1",
    "gene_TMEM63A",
    "gene_LEFTY1",
    "gene_PYCR2",
    "gene_LEFTY2",
    "gene_MIXL1",
    "gene_CDC42BPA",
    "gene_GJC2",
    "gene_OBSCN",
    "gene_RHOU",
    "gene_ACTA1",
    "gene_URB2",
    "gene_CAPN9",
    "gene_C1orf198",
    "gene_FAM89A",
    "gene_TRIM67",
    "gene_AL109810.2",
    "gene_SPRTN",
    "gene_DISC1",
    "gene_MAP3K21",
    "gene_KCNK1",
    "gene_COA6",
    "gene_RBM34",
    "gene_NID1",
    "gene_MT1HL1",
    "gene_ZP4",
    "gene_BECN2",
    "gene_MAP1LC3C",
    "gene_C1orf100",
    "gene_AL451007.3",
    "gene_KIF26B",
    "gene_AHCTF1",
    "gene_ZNF124",
    "gene_NLRP3",
    "gene_OR2B11",
    "gene_OR2C3",
    "gene_GCSAML-AS1",
    "gene_OR2G2",
    "gene_OR2G3",
    "gene_OR13G1",
    "gene_OR6F1",
    "gene_OR14A2",
    "gene_OR11L1",
    "gene_OR2AJ1",
    "gene_OR2M5",
    "gene_OR2M3",
    "gene_OR2M4",
    "gene_OR2T33",
    "gene_OR2T12",
    "gene_OR2M7",
    "gene_OR14C36",
    "gene_OR2T4",
    "gene_OR2T6",
    "gene_OR2T1",
    "gene_OR2T2",
    "gene_OR2G6",
    "gene_OR2T34",
    "gene_OR2T10",
    "gene_OR2T11",
    "gene_FAM110C",
    "gene_PXDN",
    "gene_ADI1",
    "gene_COLEC11",
    "gene_ALLC",
    "gene_DCDC2C",
    "gene_CMPK2",
    "gene_ASAP2",
    "gene_RRM2",
    "gene_E2F6",
    "gene_MYCNOS",
    "gene_MYCN",
    "gene_VSNL1",
    "gene_MSGN1",
    "gene_RDH14",
    "gene_NT5C1B",
    "gene_OSR1",
    "gene_TTC32",
    "gene_GDF7",
    "gene_TDRD15",
    "gene_MFSD2B",
    "gene_TP53I3",
    "gene_PTRHD1",
    "gene_FAM166C",
    "gene_EMILIN1",
    "gene_CGREF1",
    "gene_PRR30",
    "gene_UCN",
    "gene_SNX17",
    "gene_KRTCAP3",
    "gene_C2orf16",
    "gene_ZNF512",
    "gene_FOSL2",
    "gene_PLB1",
    "gene_PCARE",
    "gene_LBH",
    "gene_XDH",
    "gene_SRD5A2",
    "gene_SPAST",
    "gene_CRIM1",
    "gene_SULT6B1",
    "gene_RMDN2",
    "gene_GALM",
    "gene_GEMIN6",
    "gene_ARHGEF33",
    "gene_C2orf91",
    "gene_C1GALT1C1L",
    "gene_ABCG5",
    "gene_SLC3A1",
    "gene_PREPL",
    "gene_SIX2",
    "gene_TMEM247",
    "gene_FOXN2",
    "gene_STON1",
    "gene_FSHR",
    "gene_TSPYL6",
    "gene_EFEMP1",
    "gene_COMMD1",
    "gene_ETAA1",
    "gene_PROKR1",
    "gene_BMP10",
    "gene_GKN2",
    "gene_GMCL1",
    "gene_ASPRV1",
    "gene_FIGLA",
    "gene_CLEC4F",
    "gene_CD207",
    "gene_ANKRD53",
    "gene_PAIP2B",
    "gene_DYSF",
    "gene_SMYD5",
    "gene_PRADC1",
    "gene_NAT8",
    "gene_DUSP11",
    "gene_C2orf78",
    "gene_ACTG2",
    "gene_LBX2",
    "gene_TLX2",
    "gene_DQX1",
    "gene_HK2",
    "gene_EVA1A",
    "gene_REG1B",
    "gene_REG1A",
    "gene_VAMP8",
    "gene_VAMP5",
    "gene_GNLY",
    "gene_KDM3A",
    "gene_CD8A",
    "gene_PLGLB2",
    "gene_SMYD1",
    "gene_FABP1",
    "gene_TEX37",
    "gene_IGKC",
    "gene_AL845331.2",
    "gene_MAL",
    "gene_TRIM43",
    "gene_ASTL",
    "gene_DUSP2",
    "gene_FER1L5",
    "gene_CNGA3",
    "gene_LIPT1",
    "gene_LONRF2",
    "gene_PDCL3",
    "gene_TBC1D8",
    "gene_CREG2",
    "gene_IL1R1",
    "gene_IL18RAP",
    "gene_SLC9A2",
    "gene_CCDC138",
    "gene_EDAR",
    "gene_SOWAHC",
    "gene_BCL2L11",
    "gene_NT5DC4",
    "gene_IL1B",
    "gene_IL36G",
    "gene_IL36A",
    "gene_IL36RN",
    "gene_IL1F10",
    "gene_INSIG2",
    "gene_EN1",
    "gene_MARCO",
    "gene_C1QL2",
    "gene_STEAP3",
    "gene_TSN",
    "gene_TEX51",
    "gene_BIN1",
    "gene_MYO7B",
    "gene_SFT2D3",
    "gene_SMPD4",
    "gene_TUBA3E",
    "gene_GPR148",
    "gene_ANKRD30BL",
    "gene_ACMSD",
    "gene_MAP3K19",
    "gene_MCM6",
    "gene_CXCR4",
    "gene_KYNU",
    "gene_LYPD6B",
    "gene_RND3",
    "gene_RBM43",
    "gene_RIF1",
    "gene_NR4A2",
    "gene_ERMN",
    "gene_CYTIP",
    "gene_LY75",
    "gene_ITGB6",
    "gene_RBMS1",
    "gene_SLC4A10",
    "gene_GCG",
    "gene_IFIH1",
    "gene_KCNH7",
    "gene_SCN2A",
    "gene_GALNT3",
    "gene_STK39",
    "gene_NOSTRIN",
    "gene_G6PC2",
    "gene_ABCB11",
    "gene_DHRS9",
    "gene_LRP2",
    "gene_PPIG",
    "gene_PHOSPHO2",
    "gene_ERICH2",
    "gene_GAD1",
    "gene_HAT1",
    "gene_DLX1",
    "gene_PDK1",
    "gene_RAPGEF4",
    "gene_CHRNA1",
    "gene_CHN1",
    "gene_EVX2",
    "gene_HOXD12",
    "gene_HOXD11",
    "gene_HOXD9",
    "gene_HOXD3",
    "gene_TTN",
    "gene_FRZB",
    "gene_DUSP19",
    "gene_FAM171B",
    "gene_ZSWIM2",
    "gene_TFPI",
    "gene_COL3A1",
    "gene_COL5A2",
    "gene_ORMDL1",
    "gene_MSTN",
    "gene_NAB1",
    "gene_MYO1B",
    "gene_CAVIN2",
    "gene_SLC39A10",
    "gene_HECW2",
    "gene_FTCDNL1",
    "gene_KCTD18",
    "gene_NIF3L1",
    "gene_ORC2",
    "gene_CASP8",
    "gene_TRAK2",
    "gene_STRADB",
    "gene_TMEM237",
    "gene_FZD7",
    "gene_NOP58",
    "gene_GPR1",
    "gene_DYTN",
    "gene_CCNYL1",
    "gene_FZD5",
    "gene_PLEKHM3",
    "gene_CRYGD",
    "gene_CRYGC",
    "gene_CRYGB",
    "gene_MAP2",
    "gene_BARD1",
    "gene_ABCA12",
    "gene_FN1",
    "gene_IGFBP2",
    "gene_IGFBP5",
    "gene_TNP1",
    "gene_TNS1",
    "gene_CXCR2",
    "gene_CXCR1",
    "gene_GPBAR1",
    "gene_PNKD",
    "gene_SLC11A1",
    "gene_VIL1",
    "gene_TTLL4",
    "gene_PRKAG3",
    "gene_WNT6",
    "gene_WNT10A",
    "gene_CDK5R2",
    "gene_FEV",
    "gene_CRYBA2",
    "gene_IHH",
    "gene_SLC23A3",
    "gene_ATG9A",
    "gene_TUBA4A",
    "gene_TUBA4B",
    "gene_PTPRN",
    "gene_RESP18",
    "gene_DNPEP",
    "gene_SPEGNB",
    "gene_CHPF",
    "gene_INHA",
    "gene_PAX3",
    "gene_MOGAT1",
    "gene_KCNE4",
    "gene_SCG2",
    "gene_CCDC195",
    "gene_COL4A3",
    "gene_TM4SF20",
    "gene_SCYGR8",
    "gene_CCL20",
    "gene_DNER",
    "gene_FBXO36",
    "gene_SP140",
    "gene_SP100",
    "gene_SPATA3",
    "gene_HTR2B",
    "gene_NMUR1",
    "gene_NPPC",
    "gene_ALPP",
    "gene_ALPG",
    "gene_ALPI",
    "gene_CHRNG",
    "gene_EFHD1",
    "gene_KCNJ13",
    "gene_NGEF",
    "gene_NEU2",
    "gene_SAG",
    "gene_UGT1A9",
    "gene_UGT1A4",
    "gene_UGT1A1",
    "gene_MROH2A",
    "gene_SPP2",
    "gene_ARL4C",
    "gene_GBX2",
    "gene_ASB18",
    "gene_COL6A3",
    "gene_MLPH",
    "gene_RAB17",
    "gene_ESPNL",
    "gene_KLHL30",
    "gene_HES6",
    "gene_TWIST2",
    "gene_GPC1",
    "gene_DUSP28",
    "gene_KIF1A",
    "gene_AGXT",
    "gene_MAB21L4",
    "gene_BOK",
    "gene_PDCD1",
    "gene_FAM240C",
    "gene_IL5RA",
    "gene_BHLHE40",
    "gene_LMCD1",
    "gene_SRGAP3",
    "gene_ARPC4",
    "gene_CIDEC",
    "gene_ATP2B2",
    "gene_SYN2",
    "gene_PPARG",
    "gene_TSEN2",
    "gene_MKRN2",
    "gene_FBLN2",
    "gene_CHCHD4",
    "gene_LSM3",
    "gene_SLC6A6",
    "gene_CCDC174",
    "gene_RBSN",
    "gene_SH3BP5",
    "gene_GALNT15",
    "gene_RAB5A",
    "gene_PP2D1",
    "gene_NR1D2",
    "gene_OXSM",
    "gene_NEK10",
    "gene_EOMES",
    "gene_GADL1",
    "gene_CCR4",
    "gene_TMPPE",
    "gene_ITGA9",
    "gene_PLCD1",
    "gene_OXSR1",
    "gene_SLC22A13",
    "gene_SLC22A14",
    "gene_SCN5A",
    "gene_SCN10A",
    "gene_XIRP1",
    "gene_SLC25A38",
    "gene_MOBP",
    "gene_CCK",
    "gene_LYZL4",
    "gene_KLHL40",
    "gene_HHATL",
    "gene_CYP8B1",
    "gene_TOPAZ1",
    "gene_TGM4",
    "gene_TMEM158",
    "gene_CCR9",
    "gene_FYCO1",
    "gene_CXCR6",
    "gene_XCR1",
    "gene_CCR3",
    "gene_CCR1",
    "gene_LTF",
    "gene_RTP3",
    "gene_FAM240A",
    "gene_PTH1R",
    "gene_CCDC12",
    "gene_NBEAL2",
    "gene_NME6",
    "gene_ATRIP",
    "gene_UCN2",
    "gene_COL7A1",
    "gene_TMEM89",
    "gene_P4HTM",
    "gene_CCDC71",
    "gene_KLHDC8B",
    "gene_C3orf84",
    "gene_CCDC36",
    "gene_TCTA",
    "gene_AMT",
    "gene_APEH",
    "gene_CDHR4",
    "gene_TRAIP",
    "gene_CAMKV",
    "gene_SEMA3B",
    "gene_NAA80",
    "gene_HYAL2",
    "gene_CYB561D2",
    "gene_C3orf18",
    "gene_MANF",
    "gene_IQCF6",
    "gene_IQCF2",
    "gene_IQCF5",
    "gene_GLYCTK",
    "gene_TNNC1",
    "gene_STAB1",
    "gene_SMIM4",
    "gene_PBRM1",
    "gene_ITIH1",
    "gene_ITIH3",
    "gene_CHDH",
    "gene_ERC2",
    "gene_SPATA12",
    "gene_IL17RD",
    "gene_ASB14",
    "gene_DNAH12",
    "gene_ARF4",
    "gene_FAM3D",
    "gene_C3orf49",
    "gene_MITF",
    "gene_GPR27",
    "gene_PROK2",
    "gene_GXYLT2",
    "gene_PPP4R2",
    "gene_FRG2C",
    "gene_GBE1",
    "gene_CGGBP1",
    "gene_CSNKA2IP",
    "gene_EPHA3",
    "gene_STX19",
    "gene_EPHA6",
    "gene_GABRR3",
    "gene_OR5AC2",
    "gene_OR5H2",
    "gene_OR5K4",
    "gene_OR5K3",
    "gene_OR5K1",
    "gene_OR5K2",
    "gene_CLDND1",
    "gene_FILIP1L",
    "gene_TMEM45A",
    "gene_ADGRG7",
    "gene_IMPG2",
    "gene_NFKBIZ",
    "gene_ZPLD1",
    "gene_CCDC54",
    "gene_HHLA2",
    "gene_CIP2A",
    "gene_MORC1",
    "gene_C3orf85",
    "gene_DPPA2",
    "gene_DPPA4",
    "gene_CD96",
    "gene_PHLDB2",
    "gene_TAGLN3",
    "gene_C3orf52",
    "gene_GCSAM",
    "gene_CCDC80",
    "gene_CD200R1",
    "gene_GTPBP8",
    "gene_CCDC191",
    "gene_DRD3",
    "gene_TIGIT",
    "gene_TEX55",
    "gene_B4GALT4",
    "gene_CD80",
    "gene_GPR156",
    "gene_FSTL1",
    "gene_HCLS1",
    "gene_ILDR1",
    "gene_CASR",
    "gene_CSTA",
    "gene_MYLK",
    "gene_UMPS",
    "gene_MUC13",
    "gene_ZNF148",
    "gene_ALG1L",
    "gene_ALDH1L1",
    "gene_CHST13",
    "gene_C3orf56",
    "gene_TPRA1",
    "gene_SEC61A1",
    "gene_EEFSEC",
    "gene_DNAJB8",
    "gene_GATA2",
    "gene_RAB7A",
    "gene_GP9",
    "gene_ISY1",
    "gene_H1FOO",
    "gene_TRH",
    "gene_COL6A5",
    "gene_COL6A6",
    "gene_ASTE1",
    "gene_NUDT16",
    "gene_ACKR4",
    "gene_NPHP3",
    "gene_TMEM108",
    "gene_BFSP2",
    "gene_TF",
    "gene_RAB6B",
    "gene_AMOTL2",
    "gene_EPHB1",
    "gene_SOX14",
    "gene_A4GNT",
    "gene_FOXL2NB",
    "gene_PRR23A",
    "gene_PRR23C",
    "gene_RBP2",
    "gene_RBP1",
    "gene_NMNAT3",
    "gene_CLSTN2",
    "gene_TRIM42",
    "gene_XRN1",
    "gene_PLOD2",
    "gene_PLSCR2",
    "gene_PLSCR5",
    "gene_AGTR1",
    "gene_CPB1",
    "gene_CPA3",
    "gene_CP",
    "gene_TM4SF1",
    "gene_TM4SF4",
    "gene_ANKUB1",
    "gene_MINDY4B",
    "gene_CLRN1",
    "gene_GPR171",
    "gene_AADACL2",
    "gene_SUCNR1",
    "gene_RAP2B",
    "gene_GPR149",
    "gene_STRIT1",
    "gene_VEPH1",
    "gene_PTX3",
    "gene_SLC66A1L",
    "gene_SHOX2",
    "gene_RARRES1",
    "gene_IQCJ",
    "gene_C3orf80",
    "gene_KPNA4",
    "gene_ARL14",
    "gene_SPTSSB",
    "gene_OTOL1",
    "gene_SI",
    "gene_BCHE",
    "gene_WDR49",
    "gene_SERPINI1",
    "gene_TERC",
    "gene_LRRC31",
    "gene_SAMD7",
    "gene_CLDN11",
    "gene_SLC2A2",
    "gene_TMEM212",
    "gene_FNDC3B",
    "gene_GHSR",
    "gene_TNFSF10",
    "gene_SPATA16",
    "gene_TBL1XR1",
    "gene_USP13",
    "gene_LAMP3",
    "gene_MCF2L2",
    "gene_KLHL6",
    "gene_HTR3D",
    "gene_HTR3C",
    "gene_HTR3E",
    "gene_EEF1AKMT4",
    "gene_MAP3K13",
    "gene_TMEM41A",
    "gene_AHSG",
    "gene_FETUB",
    "gene_HRG",
    "gene_KNG1",
    "gene_ADIPOQ",
    "gene_SST",
    "gene_RTP2",
    "gene_AC072022.2",
    "gene_LPP",
    "gene_TP63",
    "gene_P3H2",
    "gene_CLDN16",
    "gene_GMNC",
    "gene_MB21D2",
    "gene_ATP13A5",
    "gene_CPN2",
    "gene_LRRC15",
    "gene_GP5",
    "gene_FAM43A",
    "gene_XXYLT1",
    "gene_APOD",
    "gene_MUC4",
    "gene_ZDHHC19",
    "gene_SLC51A",
    "gene_PCYT1A",
    "gene_PAK2",
    "gene_PIGZ",
    "gene_ZNF595",
    "gene_ZNF732",
    "gene_ZNF141",
    "gene_TMEM271",
    "gene_MYL5",
    "gene_SLC49A3",
    "gene_CPLX1",
    "gene_SLC26A1",
    "gene_SPON2",
    "gene_POLN",
    "gene_ZFYVE28",
    "gene_TNIP2",
    "gene_DOK7",
    "gene_MSX1",
    "gene_PPP2R2C",
    "gene_AC093323.1",
    "gene_S100P",
    "gene_MRFAP1L1",
    "gene_BLOC1S4",
    "gene_CCDC96",
    "gene_PSAPL1",
    "gene_SH3TC1",
    "gene_GPR78",
    "gene_CPZ",
    "gene_FAM90A26",
    "gene_USP17L10",
    "gene_USP17L15",
    "gene_DRD5",
    "gene_CLNK",
    "gene_NKX3-2",
    "gene_PROM1",
    "gene_CLRN2",
    "gene_LAP3",
    "gene_PPARGC1A",
    "gene_DHX15",
    "gene_SOD3",
    "gene_ZCCHC4",
    "gene_C4orf19",
    "gene_TLR6",
    "gene_KLB",
    "gene_LIAS",
    "gene_RHOH",
    "gene_RBM47",
    "gene_UCHL1",
    "gene_PHOX2B",
    "gene_SHISA3",
    "gene_GRXCR1",
    "gene_COX7B2",
    "gene_ATP10D",
    "gene_CORIN",
    "gene_NIPAL1",
    "gene_CNGA1",
    "gene_TEC",
    "gene_SLC10A4",
    "gene_ZAR1",
    "gene_FRYL",
    "gene_ERVMER34-1",
    "gene_CHIC2",
    "gene_EXOC1L",
    "gene_PPAT",
    "gene_SRP72",
    "gene_HOPX",
    "gene_SPINK2",
    "gene_TECRL",
    "gene_EPHA5",
    "gene_STAP1",
    "gene_GNRHR",
    "gene_TMPRSS11D",
    "gene_TMPRSS11E",
    "gene_UGT2B28",
    "gene_UGT2A1",
    "gene_UGT2A2",
    "gene_SULT1B1",
    "gene_CSN2",
    "gene_STATH",
    "gene_HTN1",
    "gene_PRR27",
    "gene_FDCSP",
    "gene_CSN3",
    "gene_SMR3B",
    "gene_OPRPN",
    "gene_MUC7",
    "gene_AMTN",
    "gene_AMBN",
    "gene_JCHAIN",
    "gene_GC",
    "gene_ANKRD17",
    "gene_AFP",
    "gene_AFM",
    "gene_CXCL8",
    "gene_CXCL6",
    "gene_PF4V1",
    "gene_PF4",
    "gene_PPBP",
    "gene_CXCL2",
    "gene_STBD1",
    "gene_CCNG2",
    "gene_CXCL13",
    "gene_GK2",
    "gene_ANTXR2",
    "gene_FGF5",
    "gene_CFAP299",
    "gene_BMP3",
    "gene_RASGEF1B",
    "gene_PLAC8",
    "gene_HELQ",
    "gene_ABRAXAS1",
    "gene_NKX6-1",
    "gene_KLHL8",
    "gene_DSPP",
    "gene_SPP1",
    "gene_TIGD2",
    "gene_SNCA",
    "gene_MMRN1",
    "gene_CCSER1",
    "gene_ATOH1",
    "gene_HPGDS",
    "gene_PDHA2",
    "gene_ADH4",
    "gene_ADH1A",
    "gene_C4orf17",
    "gene_SLC39A8",
    "gene_UBE2D3",
    "gene_CISD2",
    "gene_SLC9B1",
    "gene_TACR3",
    "gene_ARHGEF38",
    "gene_INTS12",
    "gene_CYP2U1",
    "gene_CASP6",
    "gene_CFI",
    "gene_GAR1",
    "gene_EGF",
    "gene_ELOVL6",
    "gene_ENPEP",
    "gene_PITX2",
    "gene_FAM241A",
    "gene_NEUROG2",
    "gene_ZGRF1",
    "gene_UGT8",
    "gene_SEC24D",
    "gene_SYNPO2",
    "gene_FABP2",
    "gene_PDE5A",
    "gene_TNIP3",
    "gene_ADAD1",
    "gene_IL21",
    "gene_ANKRD50",
    "gene_MFSD8",
    "gene_PABPC4L",
    "gene_ELF2",
    "gene_NDUFC1",
    "gene_ELMOD2",
    "gene_UCP1",
    "gene_IL15",
    "gene_GYPA",
    "gene_HHIP",
    "gene_C4orf51",
    "gene_REELD1",
    "gene_IQCM",
    "gene_MAB21L2",
    "gene_PRSS48",
    "gene_GATB",
    "gene_TIGD4",
    "gene_MND1",
    "gene_TLR2",
    "gene_SFRP2",
    "gene_FGB",
    "gene_FGA",
    "gene_FGG",
    "gene_LRAT",
    "gene_RBM46",
    "gene_ASIC5",
    "gene_GRIA2",
    "gene_TMEM144",
    "gene_C4orf46",
    "gene_C4orf45",
    "gene_TKTL2",
    "gene_SMIM31",
    "gene_APELA",
    "gene_TRIM61",
    "gene_TRIM60",
    "gene_TRIM75P",
    "gene_GK3P",
    "gene_ANXA10",
    "gene_DDX60L",
    "gene_PALLD",
    "gene_SH3RF1",
    "gene_MFAP3L",
    "gene_GALNTL6",
    "gene_HMGB2",
    "gene_HPGD",
    "gene_ADAM29",
    "gene_CLDN22",
    "gene_CDKN2AIP",
    "gene_RWDD4",
    "gene_IRF2",
    "gene_ACSL1",
    "gene_ANKRD37",
    "gene_C4orf47",
    "gene_PDLIM3",
    "gene_MTNR1A",
    "gene_ZFP42",
    "gene_TRIML1",
    "gene_FRG1",
    "gene_AHRR",
    "gene_SLC9A3",
    "gene_SLC6A18",
    "gene_SLC6A3",
    "gene_IRX1",
    "gene_FASTKD3",
    "gene_TAS2R1",
    "gene_BASP1",
    "gene_LINC02218",
    "gene_TAF11L4",
    "gene_TAF11L6",
    "gene_TAF11L8",
    "gene_TAF11L11",
    "gene_TAF11L12",
    "gene_TAF11L13",
    "gene_TAF11L14",
    "gene_H3.Y",
    "gene_PRDM9",
    "gene_C5orf22",
    "gene_NPR3",
    "gene_AMACR",
    "gene_TTC23L",
    "gene_AGXT2",
    "gene_UGT3A1",
    "gene_UGT3A2",
    "gene_GDNF",
    "gene_C7",
    "gene_MROH2B",
    "gene_C5orf51",
    "gene_FBXO4",
    "gene_SELENOP",
    "gene_ANXA2R",
    "gene_TMEM267",
    "gene_PAIP1",
    "gene_NNT",
    "gene_ISL1",
    "gene_ITGA1",
    "gene_FST",
    "gene_SNX18",
    "gene_ESM1",
    "gene_DDX4",
    "gene_ANKRD55",
    "gene_ACTBL2",
    "gene_ERCC8",
    "gene_NDUFAF2",
    "gene_SMIM15",
    "gene_HTR1A",
    "gene_SHISAL2B",
    "gene_SHLD3",
    "gene_CCNB1",
    "gene_CDK7",
    "gene_OCLN",
    "gene_TMEM171",
    "gene_TMEM174",
    "gene_FOXD1",
    "gene_UTP15",
    "gene_ENC1",
    "gene_NSA2",
    "gene_POLK",
    "gene_POC5",
    "gene_F2R",
    "gene_BHMT2",
    "gene_SPZ1",
    "gene_ANKRD34B",
    "gene_VCAN",
    "gene_TMEM161B",
    "gene_MBLAC2",
    "gene_ADGRV1",
    "gene_FAM81B",
    "gene_GPR150",
    "gene_RFESD",
    "gene_RHOBTB3",
    "gene_ELL2",
    "gene_PCSK1",
    "gene_SLCO6A1",
    "gene_FER",
    "gene_MAN2A1",
    "gene_STARD4",
    "gene_REEP5",
    "gene_TSSK1B",
    "gene_TRIM36",
    "gene_ARL14EPL",
    "gene_TNFAIP8",
    "gene_LOX",
    "gene_AC010255.3",
    "gene_TEX43",
    "gene_CCDC192",
    "gene_FBN2",
    "gene_MINAR2",
    "gene_FNIP1",
    "gene_MEIKIN",
    "gene_IL3",
    "gene_CSF2",
    "gene_PDLIM4",
    "gene_SLC22A5",
    "gene_IRF1",
    "gene_IL13",
    "gene_CCNI2",
    "gene_SEPTIN8",
    "gene_GDF9",
    "gene_CDKN2AIPNL",
    "gene_SAR1B",
    "gene_TIFAB",
    "gene_NEUROG1",
    "gene_CXCL14",
    "gene_LECT2",
    "gene_TGFBI",
    "gene_SMIM32",
    "gene_PKD2L2",
    "gene_WNT8A",
    "gene_GFRA3",
    "gene_EGR1",
    "gene_SIL1",
    "gene_MZB1",
    "gene_PROB1",
    "gene_SPATA24",
    "gene_SMIM33",
    "gene_CYSTM1",
    "gene_EIF4EBP3",
    "gene_CD14",
    "gene_DND1",
    "gene_PCDHA2",
    "gene_PCDHA10",
    "gene_PCDHB1",
    "gene_PCDHB3",
    "gene_PCDHB7",
    "gene_PCDHGA10",
    "gene_PCDHGC3",
    "gene_SPRY4",
    "gene_GRXCR2",
    "gene_POU4F3",
    "gene_GPR151",
    "gene_SPINK1",
    "gene_SCGB3A2",
    "gene_SPINK5",
    "gene_SPINK6",
    "gene_MARCOL",
    "gene_SPINK13",
    "gene_SPINK7",
    "gene_HTR4",
    "gene_ADRB2",
    "gene_SH3TC2",
    "gene_IL17B",
    "gene_PDE6A",
    "gene_CSF1R",
    "gene_PDGFRB",
    "gene_CDX1",
    "gene_CAMK2A",
    "gene_ARSI",
    "gene_SMIM3",
    "gene_IRGM",
    "gene_SLC36A2",
    "gene_FAT2",
    "gene_GLRA1",
    "gene_HAND1",
    "gene_KIF4B",
    "gene_SOX30",
    "gene_THG1L",
    "gene_IL12B",
    "gene_ZBED8",
    "gene_PTTG1",
    "gene_ATP10B",
    "gene_GABRB2",
    "gene_GABRA6",
    "gene_GABRA1",
    "gene_GABRG2",
    "gene_RARS",
    "gene_FOXI1",
    "gene_C5orf58",
    "gene_GABRP",
    "gene_TLX3",
    "gene_FGF18",
    "gene_SMIM23",
    "gene_STK10",
    "gene_EFCAB9",
    "gene_NEURL1B",
    "gene_NKX2-5",
    "gene_BOD1",
    "gene_CPEB4",
    "gene_C5orf47",
    "gene_NSG2",
    "gene_MSX2",
    "gene_CPLX2",
    "gene_SNCB",
    "gene_HK3",
    "gene_RAB24",
    "gene_LMAN2",
    "gene_PFN3",
    "gene_TMED9",
    "gene_PROP1",
    "gene_ZNF354A",
    "gene_C5orf60",
    "gene_CBY3",
    "gene_SCGB3A1",
    "gene_OR2Y1",
    "gene_MGAT1",
    "gene_BTNL8",
    "gene_OR2V1",
    "gene_OR2V2",
    "gene_TRIM7",
    "gene_HUS1B",
    "gene_FOXC1",
    "gene_TUBB2A",
    "gene_PSMG4",
    "gene_C6orf201",
    "gene_PPP1R3G",
    "gene_NRN1",
    "gene_F13A1",
    "gene_CAGE1",
    "gene_TXNDC5",
    "gene_GCNT2",
    "gene_ERVFRD-1",
    "gene_SIRT5",
    "gene_DTNBP1",
    "gene_NUP153",
    "gene_MBOAT1",
    "gene_E2F3",
    "gene_SOX4",
    "gene_PRL",
    "gene_HDGFL1",
    "gene_NRSN1",
    "gene_KAAG1",
    "gene_MRS2",
    "gene_ARMH2",
    "gene_HIST1H2BA",
    "gene_SLC17A4",
    "gene_SLC17A1",
    "gene_SLC17A2",
    "gene_TRIM38",
    "gene_HIST1H1E",
    "gene_HIST1H4E",
    "gene_HIST1H2BG",
    "gene_HIST1H2AE",
    "gene_HIST1H1D",
    "gene_HIST1H4G",
    "gene_HIST1H2BH",
    "gene_HIST1H3G",
    "gene_BTN2A2",
    "gene_HIST1H2AG",
    "gene_POM121L2",
    "gene_ZNF184",
    "gene_HIST1H3H",
    "gene_HIST1H1B",
    "gene_OR2B2",
    "gene_OR2B6",
    "gene_ZSCAN9",
    "gene_ZKSCAN4",
    "gene_NKAPL",
    "gene_ZSCAN31",
    "gene_GPX5",
    "gene_OR2W1",
    "gene_OR2B3",
    "gene_OR2J3",
    "gene_OR14J1",
    "gene_OR5V1",
    "gene_OR12D3",
    "gene_OR11A1",
    "gene_OR10C1",
    "gene_OR2H1",
    "gene_OR2H2",
    "gene_MOG",
    "gene_ZFP57",
    "gene_RNF39",
    "gene_TRIM40",
    "gene_TRIM15",
    "gene_IER3",
    "gene_SFTA2",
    "gene_MUCL3",
    "gene_MUC21",
    "gene_MUC22",
    "gene_C6orf15",
    "gene_PSORS1C2",
    "gene_MCCD1",
    "gene_ATP6V1G2",
    "gene_LTA",
    "gene_LTB",
    "gene_NCR3",
    "gene_C6orf47",
    "gene_LY6G6F",
    "gene_LY6G6E",
    "gene_LY6G6D",
    "gene_MPIG6B",
    "gene_LY6G6C",
    "gene_DDAH2",
    "gene_CLIC1",
    "gene_HSPA1A",
    "gene_HSPA1B",
    "gene_SLC44A4",
    "gene_C2",
    "gene_ZBTB12",
    "gene_CFB",
    "gene_CYP21A2",
    "gene_TNXB",
    "gene_PRRT1",
    "gene_EGFL8",
    "gene_AGPAT1",
    "gene_AGER",
    "gene_TSBP1",
    "gene_PSMB9",
    "gene_VPS52",
    "gene_B3GALT4",
    "gene_TAPBP",
    "gene_ZBTB9",
    "gene_BAK1",
    "gene_GRM4",
    "gene_HMGA1",
    "gene_PACSIN1",
    "gene_TAF11",
    "gene_TULP1",
    "gene_ARMC12",
    "gene_CLPSL2",
    "gene_CLPS",
    "gene_PNPLA1",
    "gene_BNIP5",
    "gene_PXT1",
    "gene_CDKN1A",
    "gene_C6orf89",
    "gene_TMEM217",
    "gene_TBC1D22B",
    "gene_DNAH8",
    "gene_GLP1R",
    "gene_SAYSD1",
    "gene_KCNK5",
    "gene_DAAM2",
    "gene_TSPO2",
    "gene_APOBEC2",
    "gene_TREM2",
    "gene_TREM1",
    "gene_USP49",
    "gene_C6orf132",
    "gene_C6orf226",
    "gene_MEA1",
    "gene_PTK7",
    "gene_DNPH1",
    "gene_SLC22A7",
    "gene_VEGFA",
    "gene_C6orf223",
    "gene_CAPN11",
    "gene_MYMX",
    "gene_RCAN2",
    "gene_ANKRD66",
    "gene_MEP1A",
    "gene_ADGRF1",
    "gene_ADGRF2",
    "gene_CENPQ",
    "gene_RHAG",
    "gene_DEFB133",
    "gene_DEFB114",
    "gene_DEFB112",
    "gene_TFAP2D",
    "gene_IL17F",
    "gene_MCM3",
    "gene_EFHC1",
    "gene_TRAM2",
    "gene_GSTA1",
    "gene_GSTA5",
    "gene_GSTA3",
    "gene_GCM1",
    "gene_GCLC",
    "gene_KLHL31",
    "gene_TINAG",
    "gene_FAM83B",
    "gene_GFRAL",
    "gene_BMP5",
    "gene_BAG2",
    "gene_PRIM2",
    "gene_FKBP1C",
    "gene_EYS",
    "gene_DPPA5",
    "gene_KHDC3L",
    "gene_OOEP",
    "gene_MTO1",
    "gene_IMPG1",
    "gene_TENT5A",
    "gene_SNAP91",
    "gene_ZNF292",
    "gene_GJB7",
    "gene_SMIM8",
    "gene_CNR1",
    "gene_GABRR1",
    "gene_ANKRD6",
    "gene_GJA10",
    "gene_SIM1",
    "gene_LIN28B",
    "gene_CRYBG1",
    "gene_CD24",
    "gene_SCML4",
    "gene_CD164",
    "gene_ZBTB24",
    "gene_AK9",
    "gene_WASF1",
    "gene_GTF3C6",
    "gene_CCN6",
    "gene_LAMA4",
    "gene_DSE",
    "gene_CALHM6",
    "gene_TRAPPC3L",
    "gene_CALHM5",
    "gene_CALHM4",
    "gene_GPRC6A",
    "gene_RFX6",
    "gene_VGLL2",
    "gene_FABP7",
    "gene_THEMIS",
    "gene_SMLR1",
    "gene_ARG1",
    "gene_CCN2",
    "gene_STX7",
    "gene_TAAR9",
    "gene_TAAR8",
    "gene_TAAR6",
    "gene_TAAR5",
    "gene_TAAR2",
    "gene_TAAR1",
    "gene_VNN1",
    "gene_VNN3",
    "gene_EYA4",
    "gene_TCF21",
    "gene_SGK1",
    "gene_MTFR2",
    "gene_SLC35D3",
    "gene_IL20RA",
    "gene_IFNGR1",
    "gene_TNFAIP3",
    "gene_PBOV1",
    "gene_SMIM28",
    "gene_ECT2L",
    "gene_ABRACL",
    "gene_NMBR",
    "gene_GJE1",
    "gene_HIVEP2",
    "gene_PLAGL1",
    "gene_STX11",
    "gene_SUMO4",
    "gene_ZC3H12D",
    "gene_RAET1G",
    "gene_ULBP1",
    "gene_RAET1L",
    "gene_PLEKHG1",
    "gene_AKAP12",
    "gene_ZBTB2",
    "gene_RMND1",
    "gene_ESR1",
    "gene_SYNE1",
    "gene_MTRF1L",
    "gene_RGS17",
    "gene_CLDN20",
    "gene_DYNLT1",
    "gene_FNDC1",
    "gene_SOD2",
    "gene_PNLDC1",
    "gene_SLC22A2",
    "gene_PLG",
    "gene_PRKN",
    "gene_PDE10A",
    "gene_TBXT",
    "gene_PRR18",
    "gene_TCP10L2",
    "gene_GPR31",
    "gene_UNC93A",
    "gene_TTLL2",
    "gene_KIF25",
    "gene_DACT2",
    "gene_THBS2",
    "gene_FAM20C",
    "gene_AC187653.1",
    "gene_PRKAR1B",
    "gene_CYP2W1",
    "gene_GPER1",
    "gene_ZFAND2A",
    "gene_UNCX",
    "gene_MAFK",
    "gene_TMEM184A",
    "gene_EIF3B",
    "gene_CHST12",
    "gene_GRIFIN",
    "gene_LFNG",
    "gene_BRAT1",
    "gene_SDK1",
    "gene_AP5Z1",
    "gene_PAPOLB",
    "gene_SLC29A4",
    "gene_ACTB",
    "gene_AIMP2",
    "gene_ANKRD61",
    "gene_USP42",
    "gene_CYTH3",
    "gene_ZNF853",
    "gene_ZNF316",
    "gene_AC013470.2",
    "gene_SCIN",
    "gene_ARL4A",
    "gene_MEOX2",
    "gene_LRRC72",
    "gene_AGR2",
    "gene_AGR3",
    "gene_PRPS1L1",
    "gene_TWIST1",
    "gene_FERD3L",
    "gene_ABCB5",
    "gene_CDCA7L",
    "gene_IL6",
    "gene_GPNMB",
    "gene_IGF2BP3",
    "gene_FAM221A",
    "gene_NPY",
    "gene_CYCS",
    "gene_C7orf31",
    "gene_NPVF",
    "gene_NFE2L3",
    "gene_HOXA1",
    "gene_HOXA2",
    "gene_HOXA3",
    "gene_HOXA6",
    "gene_HOXA9",
    "gene_HOXA11",
    "gene_HOXA13",
    "gene_EVX1",
    "gene_TRIL",
    "gene_CPVL",
    "gene_AC004593.3",
    "gene_PRR15",
    "gene_ZNRF2",
    "gene_GARS",
    "gene_INMT",
    "gene_AQP1",
    "gene_NEUROD6",
    "gene_ITPRID1",
    "gene_PPP1R17",
    "gene_NPSR1",
    "gene_DPY19L1",
    "gene_KIAA0895",
    "gene_ANLN",
    "gene_NME8",
    "gene_SFRP4",
    "gene_TRGC1",
    "gene_AMPH",
    "gene_SUGCT",
    "gene_GLI3",
    "gene_SPDYE1",
    "gene_PGAM2",
    "gene_AEBP1",
    "gene_MYL7",
    "gene_GCK",
    "gene_CAMK2B",
    "gene_NPC1L1",
    "gene_RAMP3",
    "gene_CCDC201",
    "gene_IGFBP3",
    "gene_PKD1L1",
    "gene_SUN3",
    "gene_ZPBP",
    "gene_IKZF1",
    "gene_FIGNL1",
    "gene_DDC",
    "gene_GRB10",
    "gene_POM121L12",
    "gene_VSTM2A",
    "gene_SEC61G",
    "gene_LANCL2",
    "gene_SEPTIN14",
    "gene_PHKG1",
    "gene_NUPR2",
    "gene_ZNF479",
    "gene_ZNF716",
    "gene_AC115220.1",
    "gene_ZNF735",
    "gene_ZNF679",
    "gene_FKBP6",
    "gene_FZD9",
    "gene_DNAJC30",
    "gene_STX1A",
    "gene_ABHD11",
    "gene_CLDN3",
    "gene_CLDN4",
    "gene_METTL27",
    "gene_TMEM270",
    "gene_ELN",
    "gene_LAT2",
    "gene_SPDYE5",
    "gene_CCL24",
    "gene_SSC4D",
    "gene_FGL2",
    "gene_GSAP",
    "gene_TMEM60",
    "gene_GNAT3",
    "gene_HGF",
    "gene_PCLO",
    "gene_TMEM243",
    "gene_CROT",
    "gene_TEX47",
    "gene_STEAP1",
    "gene_STEAP2",
    "gene_CFAP69",
    "gene_FAM237B",
    "gene_FZD1",
    "gene_LRRD1",
    "gene_RBM48",
    "gene_FAM133B",
    "gene_CDK6",
    "gene_SAMD9",
    "gene_HEPACAM2",
    "gene_CALCR",
    "gene_GNGT1",
    "gene_COL1A2",
    "gene_PON3",
    "gene_PDK4",
    "gene_SLC25A13",
    "gene_SDHAF3",
    "gene_TAC1",
    "gene_OCM2",
    "gene_TMEM130",
    "gene_KPNA7",
    "gene_ARPC1B",
    "gene_PTCD1",
    "gene_CPSF4",
    "gene_ZNF394",
    "gene_ZSCAN25",
    "gene_CYP3A7",
    "gene_CYP3A4",
    "gene_OR2AE1",
    "gene_GJC3",
    "gene_AZGP1",
    "gene_MCM7",
    "gene_PPP1R35",
    "gene_C7orf61",
    "gene_NYAP1",
    "gene_FBXO24",
    "gene_PCOLCE",
    "gene_MOSPD3",
    "gene_EPO",
    "gene_ZAN",
    "gene_EPHB4",
    "gene_UFSP1",
    "gene_MUC3A",
    "gene_MUC12",
    "gene_MUC17",
    "gene_SERPINE1",
    "gene_VGF",
    "gene_NAT16",
    "gene_MOGAT3",
    "gene_PLOD3",
    "gene_CLDN15",
    "gene_MYL10",
    "gene_SPDYE6",
    "gene_ALKBH4",
    "gene_SLC26A5",
    "gene_RELN",
    "gene_ORC5",
    "gene_EFCAB10",
    "gene_ATXN7L1",
    "gene_NAMPT",
    "gene_CCDC71L",
    "gene_PIK3CG",
    "gene_DUS4L",
    "gene_SLC26A3",
    "gene_LAMB1",
    "gene_LAMB4",
    "gene_DNAJB9",
    "gene_IMMP2L",
    "gene_GPR85",
    "gene_SMIM30",
    "gene_PPP1R3A",
    "gene_FOXP2",
    "gene_MDFIC",
    "gene_TES",
    "gene_CAV2",
    "gene_CAV1",
    "gene_MET",
    "gene_CTTNBP2",
    "gene_ANKRD7",
    "gene_KCND2",
    "gene_TSPAN12",
    "gene_CPED1",
    "gene_FEZF1",
    "gene_TAS2R16",
    "gene_ASB15",
    "gene_LMOD2",
    "gene_HYAL4",
    "gene_TMEM229A",
    "gene_SSU72P8",
    "gene_GPR37",
    "gene_GCC1",
    "gene_FSCN3",
    "gene_PAX4",
    "gene_LEP",
    "gene_PRRT4",
    "gene_HILPDA",
    "gene_OPN1SW",
    "gene_ATP6V1FNB",
    "gene_IRF5",
    "gene_AC011005.1",
    "gene_SMO",
    "gene_SMKR1",
    "gene_SSMEM1",
    "gene_CPA2",
    "gene_CPA4",
    "gene_CPA5",
    "gene_CPA1",
    "gene_KLF14",
    "gene_CALD1",
    "gene_TMEM140",
    "gene_STRA8",
    "gene_SLC13A4",
    "gene_AKR1D1",
    "gene_SVOPL",
    "gene_ATP6V0A4",
    "gene_TMEM213",
    "gene_TTC26",
    "gene_KLRG2",
    "gene_HIPK2",
    "gene_KDM7A",
    "gene_SLC37A3",
    "gene_DENND11",
    "gene_WEE2",
    "gene_SSBP1",
    "gene_TAS2R4",
    "gene_PRSS37",
    "gene_MGAM",
    "gene_CLEC5A",
    "gene_TAS2R38",
    "gene_PRSS1",
    "gene_TRBC1",
    "gene_LLCFC1",
    "gene_OR6V1",
    "gene_TAS2R39",
    "gene_CLCN1",
    "gene_EPHA1",
    "gene_OR2F2",
    "gene_OR2F1",
    "gene_OR6B1",
    "gene_OR2A5",
    "gene_OR2A25",
    "gene_OR2A12",
    "gene_OR2A2",
    "gene_OR2A14",
    "gene_ARHGEF35",
    "gene_NOBOX",
    "gene_C7orf33",
    "gene_ZNF786",
    "gene_ZNF783",
    "gene_ZNF777",
    "gene_KRBA1",
    "gene_ZBED6CL",
    "gene_ZNF775",
    "gene_AC073111.4",
    "gene_GIMAP8",
    "gene_GIMAP4",
    "gene_GIMAP6",
    "gene_GIMAP2",
    "gene_GIMAP1",
    "gene_TMEM176A",
    "gene_KCNH2",
    "gene_FASTK",
    "gene_TMUB1",
    "gene_AGAP3",
    "gene_GBX1",
    "gene_ASB10",
    "gene_IQCA1L",
    "gene_HTR5A",
    "gene_EN2",
    "gene_SHH",
    "gene_MNX1",
    "gene_PTPRN2",
    "gene_VIPR2",
    "gene_OR4F21",
    "gene_XKR5",
    "gene_DEFB1",
    "gene_DEFA6",
    "gene_DEFA4",
    "gene_DEFA5",
    "gene_USP17L1",
    "gene_ZNF705G",
    "gene_AC134684.8",
    "gene_DEFB4A",
    "gene_USP17L3",
    "gene_PRAG1",
    "gene_CLDN23",
    "gene_PPP1R3B",
    "gene_PRSS55",
    "gene_RP1L1",
    "gene_C8orf74",
    "gene_SLC35G5",
    "gene_DEFB136",
    "gene_DEFB135",
    "gene_USP17L7",
    "gene_USP17L2",
    "gene_DLC1",
    "gene_MSR1",
    "gene_CNOT7",
    "gene_VPS37A",
    "gene_SH2D4A",
    "gene_SLC18A1",
    "gene_DMTN",
    "gene_REEP4",
    "gene_LGI3",
    "gene_BMP1",
    "gene_PHYHIP",
    "gene_SLC39A14",
    "gene_SORBS3",
    "gene_BIN3",
    "gene_EGR3",
    "gene_LOXL2",
    "gene_NKX3-1",
    "gene_NKX2-6",
    "gene_ADAM7",
    "gene_NEFM",
    "gene_NEFL",
    "gene_DOCK5",
    "gene_KCTD9",
    "gene_EBF2",
    "gene_SCARA3",
    "gene_ESCO2",
    "gene_ELP3",
    "gene_PNOC",
    "gene_MBOAT4",
    "gene_SMIM18",
    "gene_NRG1",
    "gene_KCNU1",
    "gene_BRF2",
    "gene_GOT1L1",
    "gene_EIF4EBP1",
    "gene_LETM2",
    "gene_HTRA4",
    "gene_ADAM32",
    "gene_IDO1",
    "gene_IDO2",
    "gene_TCIM",
    "gene_NKX6-3",
    "gene_ANK1",
    "gene_DKK4",
    "gene_CHRNA6",
    "gene_THAP1",
    "gene_SNAI2",
    "gene_PPDPFL",
    "gene_ALKAL1",
    "gene_NPBWR1",
    "gene_ATP6V1H",
    "gene_RGS20",
    "gene_PENK",
    "gene_CYP7A1",
    "gene_CHD7",
    "gene_BHLHE22",
    "gene_DNAJC5B",
    "gene_TRIM55",
    "gene_CRH",
    "gene_RRS1",
    "gene_VXN",
    "gene_C8orf34",
    "gene_PRDM14",
    "gene_TERF1",
    "gene_C8orf89",
    "gene_RDH10",
    "gene_IL7",
    "gene_STMN2",
    "gene_FABP12",
    "gene_SNX16",
    "gene_CA1",
    "gene_CA3",
    "gene_ATP6V0D2",
    "gene_SLC7A13",
    "gene_WWP1",
    "gene_CNBD1",
    "gene_DCAF4L2",
    "gene_RIPK2",
    "gene_TMEM64",
    "gene_SLC26A7",
    "gene_GEM",
    "gene_ESRP1",
    "gene_GDF6",
    "gene_ERICH5",
    "gene_STK3",
    "gene_FBXO43",
    "gene_SNX31",
    "gene_GRHL2",
    "gene_ODF1",
    "gene_ATP6V1C1",
    "gene_CTHRC1",
    "gene_UTP23",
    "gene_AARD",
    "gene_TNFRSF11B",
    "gene_COLEC10",
    "gene_ENPP2",
    "gene_TAF2",
    "gene_DEPTOR",
    "gene_COL14A1",
    "gene_TBC1D31",
    "gene_FAM83A",
    "gene_C8orf76",
    "gene_WDYHV1",
    "gene_ANXA13",
    "gene_NSMCE2",
    "gene_LRATD2",
    "gene_POU5F1B",
    "gene_MYC",
    "gene_OC90",
    "gene_HHLA1",
    "gene_LRRC6",
    "gene_SLA",
    "gene_CCN4",
    "gene_NDRG1",
    "gene_ZFAT",
    "gene_COL22A1",
    "gene_AGO2",
    "gene_DENND3",
    "gene_GPR20",
    "gene_AC138647.1",
    "gene_PSCA",
    "gene_LY6K",
    "gene_THEM6",
    "gene_SLURP1",
    "gene_LYPD2",
    "gene_SLURP2",
    "gene_CYP11B1",
    "gene_LY6H",
    "gene_GPIHBP1",
    "gene_GLI4",
    "gene_MAFA",
    "gene_GSDMD",
    "gene_TIGD5",
    "gene_PYCR3",
    "gene_CCDC166",
    "gene_IQANK1",
    "gene_SCX",
    "gene_SLC52A2",
    "gene_FBXL6",
    "gene_ADCK5",
    "gene_MFSD3",
    "gene_ZNF7",
    "gene_FOXD4",
    "gene_KANK1",
    "gene_DMRT1",
    "gene_DMRT2",
    "gene_KCNV2",
    "gene_PUM3",
    "gene_GLIS3",
    "gene_PLPP6",
    "gene_INSL6",
    "gene_INSL4",
    "gene_RLN2",
    "gene_RLN1",
    "gene_RIC1",
    "gene_KIAA2026",
    "gene_MLANA",
    "gene_IL33",
    "gene_TPD52L3",
    "gene_GLDC",
    "gene_DMAC1",
    "gene_TYRP1",
    "gene_LURAP1L",
    "gene_MPDZ",
    "gene_NFIB",
    "gene_CER1",
    "gene_BNC2",
    "gene_SH3GL2",
    "gene_ADAMTSL1",
    "gene_PLIN2",
    "gene_IFNB1",
    "gene_IFNW1",
    "gene_IFNA4",
    "gene_IFNA7",
    "gene_IFNA16",
    "gene_IFNA14",
    "gene_IFNA5",
    "gene_IFNA8",
    "gene_IFNA1",
    "gene_CDKN2B",
    "gene_DMRTA1",
    "gene_ELAVL2",
    "gene_IZUMO3",
    "gene_TUSC1",
    "gene_LRRC19",
    "gene_IFNK",
    "gene_C9orf72",
    "gene_TOPORS",
    "gene_SMIM27",
    "gene_NDUFB6",
    "gene_TAF1L",
    "gene_B4GALT1",
    "gene_NFX1",
    "gene_AQP7",
    "gene_RPP25L",
    "gene_CCL19",
    "gene_CCL21",
    "gene_FAM205A",
    "gene_FAM205C",
    "gene_C9orf131",
    "gene_FAM166B",
    "gene_CD72",
    "gene_CCDC107",
    "gene_CA9",
    "gene_TPM2",
    "gene_FAM221B",
    "gene_OR2S2",
    "gene_GLIPR2",
    "gene_GNE",
    "gene_PAX5",
    "gene_SLC25A51",
    "gene_SHB",
    "gene_FAM240B",
    "gene_SPATA31A1",
    "gene_FOXD4L6",
    "gene_SPATA31A6",
    "gene_SPATA31A7",
    "gene_FOXD4L5",
    "gene_ZNF658",
    "gene_PGM5",
    "gene_TMEM252",
    "gene_PRKACG",
    "gene_FXN",
    "gene_C9orf135",
    "gene_C9orf85",
    "gene_C9orf57",
    "gene_GDA",
    "gene_FOXB2",
    "gene_TLE1",
    "gene_SPATA31D1",
    "gene_IDNK",
    "gene_C9orf64",
    "gene_SLC28A3",
    "gene_GAS1",
    "gene_DAPK1",
    "gene_CTSL",
    "gene_SPATA31E1",
    "gene_AL353572.3",
    "gene_NXNL2",
    "gene_S1PR3",
    "gene_CKS2",
    "gene_DIRAS2",
    "gene_NFIL3",
    "gene_CENPP",
    "gene_ASPN",
    "gene_ECM2",
    "gene_ZNF484",
    "gene_PHF2",
    "gene_FBP2",
    "gene_FBP1",
    "gene_TDRD7",
    "gene_FOXE1",
    "gene_HEMGN",
    "gene_GABBR2",
    "gene_TGFBR1",
    "gene_NR4A3",
    "gene_ERP44",
    "gene_PLPPR1",
    "gene_PPP3R2",
    "gene_CYLC2",
    "gene_OR13F1",
    "gene_OR13C3",
    "gene_OR13C5",
    "gene_OR13C9",
    "gene_SLC44A1",
    "gene_TAL2",
    "gene_ACTL7B",
    "gene_ACTL7A",
    "gene_CTNNAL1",
    "gene_FRRS1L",
    "gene_C9orf152",
    "gene_SVEP1",
    "gene_MUSK",
    "gene_LPAR1",
    "gene_OR2K2",
    "gene_DNAJC25",
    "gene_UGCG",
    "gene_SNX30",
    "gene_SLC46A2",
    "gene_ZNF883",
    "gene_SLC31A2",
    "gene_SLC31A1",
    "gene_CDC26",
    "gene_RNF183",
    "gene_ORM1",
    "gene_AKNA",
    "gene_WHRN",
    "gene_TEX53",
    "gene_TEX48",
    "gene_DEC1",
    "gene_TNC",
    "gene_BRINP1",
    "gene_PHF19",
    "gene_TRAF1",
    "gene_CNTRL",
    "gene_MORN5",
    "gene_RBM18",
    "gene_PTGS1",
    "gene_OR1J1",
    "gene_OR1N1",
    "gene_OR1N2",
    "gene_OR1B1",
    "gene_OR1L3",
    "gene_OR1K1",
    "gene_ZBTB26",
    "gene_CRB2",
    "gene_ADGRD2",
    "gene_NR5A1",
    "gene_HSPA5",
    "gene_LMX1B",
    "gene_ZBTB34",
    "gene_RALGPS1",
    "gene_STXBP1",
    "gene_FPGS",
    "gene_ENG",
    "gene_ST6GALNAC4",
    "gene_FAM102A",
    "gene_DNM1",
    "gene_COQ4",
    "gene_CERCAM",
    "gene_PKN3",
    "gene_SPOUT1",
    "gene_NTMT1",
    "gene_C9orf50",
    "gene_PRRX2",
    "gene_PTGES",
    "gene_NCS1",
    "gene_ASS1",
    "gene_QRFP",
    "gene_LAMC3",
    "gene_AIF1L",
    "gene_PRRT1B",
    "gene_BARHL1",
    "gene_GFI1B",
    "gene_GBGT1",
    "gene_ABO",
    "gene_SURF6",
    "gene_ADAMTS13",
    "gene_CACFD1",
    "gene_MYMK",
    "gene_FAM163B",
    "gene_SARDH",
    "gene_COL5A1",
    "gene_FCN2",
    "gene_OLFM1",
    "gene_LCN1",
    "gene_OBP2A",
    "gene_PAEP",
    "gene_GLT6D1",
    "gene_LCN9",
    "gene_LHX3",
    "gene_CCDC187",
    "gene_DNLZ",
    "gene_CARD9",
    "gene_EGFL7",
    "gene_LCN10",
    "gene_LCN8",
    "gene_RABL6",
    "gene_AJM1",
    "gene_PHPT1",
    "gene_TRAF2",
    "gene_C8G",
    "gene_LCNL1",
    "gene_FUT7",
    "gene_SAPCD2",
    "gene_GRIN1",
    "gene_TMEM210",
    "gene_TPRN",
    "gene_NDOR1",
    "gene_BX255925.3",
    "gene_CYSRT1",
    "gene_RNF224",
    "gene_FAM166A",
    "gene_STPG3",
    "gene_TOR4A",
    "gene_NRARP",
    "gene_EXD3",
    "gene_ENTPD8",
    "gene_EHMT1",
    "gene_AKR1C8P",
    "gene_CALML3",
    "gene_IL15RA",
    "gene_GATA3",
    "gene_USP6NL",
    "gene_CAMK1D",
    "gene_UCMA",
    "gene_SEPHS1",
    "gene_FAM107B",
    "gene_HSPA14",
    "gene_MEIG1",
    "gene_OLAH",
    "gene_RPP38",
    "gene_HACD1",
    "gene_SKIDA1",
    "gene_SPAG6",
    "gene_PIP4K2A",
    "gene_PTF1A",
    "gene_GAD2",
    "gene_ARMC4",
    "gene_MAP3K8",
    "gene_LYZL2",
    "gene_GJD4",
    "gene_FXYD4",
    "gene_C10orf142",
    "gene_CXCL12",
    "gene_TMEM72",
    "gene_RASSF4",
    "gene_DEPP1",
    "gene_ALOX5",
    "gene_MSMB",
    "gene_ANTXRL",
    "gene_GPRIN2",
    "gene_GDF2",
    "gene_ANXA8",
    "gene_FAM170B",
    "gene_DRGX",
    "gene_CHAT",
    "gene_C10orf53",
    "gene_ASAH2",
    "gene_PRKG1",
    "gene_PCDH15",
    "gene_IPMK",
    "gene_FAM13C",
    "gene_RHOBTB1",
    "gene_RTKN2",
    "gene_NRBF2",
    "gene_CTNNA3",
    "gene_CCAR1",
    "gene_NEUROG3",
    "gene_TYSND1",
    "gene_NPFFR1",
    "gene_LRRC20",
    "gene_PALD1",
    "gene_UNC5B",
    "gene_CDH23",
    "gene_OIT3",
    "gene_P4HA1",
    "gene_SYNPO2L",
    "gene_CHCHD1",
    "gene_PLAU",
    "gene_DUSP13",
    "gene_ZNF503",
    "gene_LRMDA",
    "gene_ZCCHC24",
    "gene_NUTM2E",
    "gene_GHITM",
    "gene_LRIT1",
    "gene_OPN4",
    "gene_BMPR1A",
    "gene_SNCG",
    "gene_ADIRF",
    "gene_NUTM2A",
    "gene_MINPP1",
    "gene_KLLN",
    "gene_LIPJ",
    "gene_ANKRD22",
    "gene_ACTA2",
    "gene_CH25H",
    "gene_IFIT1B",
    "gene_HTR7",
    "gene_ANKRD1",
    "gene_CYP26C1",
    "gene_FFAR4",
    "gene_PDE6C",
    "gene_OPALIN",
    "gene_FRAT2",
    "gene_UBTD1",
    "gene_HPSE2",
    "gene_NKX2-3",
    "gene_ABCC2",
    "gene_CPN1",
    "gene_SCD",
    "gene_WNT8B",
    "gene_SLF2",
    "gene_KAZALD1",
    "gene_TLX1",
    "gene_LBX1",
    "gene_LDB1",
    "gene_ELOVL3",
    "gene_PITX3",
    "gene_C10orf95",
    "gene_CYP17A1",
    "gene_RPEL1",
    "gene_PCGF6",
    "gene_STN1",
    "gene_SLK",
    "gene_COL17A1",
    "gene_ITPRIP",
    "gene_SMC3",
    "gene_HABP2",
    "gene_CASP7",
    "gene_PLEKHS1",
    "gene_ATRNL1",
    "gene_PNLIP",
    "gene_SHTN1",
    "gene_DENND10",
    "gene_TIAL1",
    "gene_ARMS2",
    "gene_DMBT1",
    "gene_AL603764.2",
    "gene_CUZD1",
    "gene_HMX3",
    "gene_HMX2",
    "gene_CTBP2",
    "gene_MMP21",
    "gene_DOCK1",
    "gene_NPS",
    "gene_CLRN3",
    "gene_TCERG1L",
    "gene_PWWP2B",
    "gene_NKX6-2",
    "gene_UTF1",
    "gene_VENTX",
    "gene_CALY",
    "gene_FUOM",
    "gene_PAOX",
    "gene_SPRN",
    "gene_ODF3",
    "gene_IRF7",
    "gene_CDHR5",
    "gene_SCT",
    "gene_TMEM80",
    "gene_PANO1",
    "gene_POLR2L",
    "gene_TSPAN4",
    "gene_MUC6",
    "gene_MUC2",
    "gene_MUC5AC",
    "gene_MUC5B",
    "gene_DUSP8",
    "gene_SYT8",
    "gene_LSP1",
    "gene_PRR33",
    "gene_TNNT3",
    "gene_AC132217.2",
    "gene_ASCL2",
    "gene_C11orf21",
    "gene_TSPAN32",
    "gene_CD81",
    "gene_TRPM5",
    "gene_CDKN1C",
    "gene_SLC22A18AS",
    "gene_NAP1L4",
    "gene_MRGPRG",
    "gene_MRGPRE",
    "gene_ART5",
    "gene_ART1",
    "gene_CHRNA10",
    "gene_OR52M1",
    "gene_C11orf40",
    "gene_OR52I2",
    "gene_OR52I1",
    "gene_OR51D1",
    "gene_OR51E1",
    "gene_OR51E2",
    "gene_OR51C1P",
    "gene_MMP26",
    "gene_OR51F1",
    "gene_OR52R1",
    "gene_OR51F2",
    "gene_OR51T1",
    "gene_OR51G2",
    "gene_OR51G1",
    "gene_OR51A4",
    "gene_OR51L1",
    "gene_OR52J3",
    "gene_OR52A1",
    "gene_OR51V1",
    "gene_HBB",
    "gene_HBD",
    "gene_OR51Q1",
    "gene_UBQLN3",
    "gene_UBQLNL",
    "gene_OR52N5",
    "gene_OR52N1",
    "gene_OR52N2",
    "gene_OR52E8",
    "gene_OR56A3",
    "gene_OR56A5",
    "gene_OR52L1",
    "gene_OR56A4",
    "gene_OR56A1",
    "gene_OR52B2",
    "gene_CCKBR",
    "gene_CAVIN3",
    "gene_OR2AG1",
    "gene_OR10A5",
    "gene_OR10A2",
    "gene_OR10A4",
    "gene_OR2D3",
    "gene_SYT9",
    "gene_OR10A6",
    "gene_OR10A3",
    "gene_NLRP10",
    "gene_TRIM66",
    "gene_C11orf16",
    "gene_ASCL3",
    "gene_WEE1",
    "gene_ADM",
    "gene_PTH",
    "gene_CALCB",
    "gene_PLEKHA7",
    "gene_OTOG",
    "gene_MYOD1",
    "gene_TPH1",
    "gene_MRGPRX4",
    "gene_HPS5",
    "gene_IGSF22",
    "gene_MRGPRX2",
    "gene_DBX1",
    "gene_PRMT3",
    "gene_SVIP",
    "gene_SLC5A12",
    "gene_FIBIN",
    "gene_BBOX1",
    "gene_BDNF",
    "gene_METTL15",
    "gene_FSHB",
    "gene_DCDC1",
    "gene_IMMP1L",
    "gene_ELP4",
    "gene_HIPK3",
    "gene_ABTB2",
    "gene_ELF5",
    "gene_EHF",
    "gene_APIP",
    "gene_PDHX",
    "gene_CD44",
    "gene_SLC1A2",
    "gene_TRAF6",
    "gene_RAG1",
    "gene_RAG2",
    "gene_TTC17",
    "gene_ALKBH3",
    "gene_C11orf96",
    "gene_ACCSL",
    "gene_SLC35C1",
    "gene_C11orf94",
    "gene_LARGE2",
    "gene_MDK",
    "gene_F2",
    "gene_PACSIN3",
    "gene_MYBPC3",
    "gene_RAPSN",
    "gene_OR4B1",
    "gene_OR4X1",
    "gene_OR4S1",
    "gene_OR4C3",
    "gene_OR4C5",
    "gene_TRIM64C",
    "gene_FOLH1",
    "gene_OR4C13",
    "gene_OR4C46",
    "gene_OR4A15",
    "gene_OR4C15",
    "gene_OR4C16",
    "gene_OR4C11",
    "gene_OR4P4",
    "gene_OR4S2",
    "gene_OR5D3P",
    "gene_OR5D13",
    "gene_OR5D14",
    "gene_OR5L1",
    "gene_OR5D18",
    "gene_OR5L2",
    "gene_OR5D16",
    "gene_OR5W2",
    "gene_OR5I1",
    "gene_OR5F1",
    "gene_OR5AS1",
    "gene_OR8I2",
    "gene_OR8H2",
    "gene_OR8H3",
    "gene_OR8K5",
    "gene_OR5J2",
    "gene_OR5T2",
    "gene_OR5T1",
    "gene_OR8H1",
    "gene_OR8K3",
    "gene_OR8J1",
    "gene_OR8U1",
    "gene_OR5R1",
    "gene_OR5M3",
    "gene_OR5M11",
    "gene_OR5M10",
    "gene_OR5M1",
    "gene_OR5AP2",
    "gene_OR5AR1",
    "gene_OR9G1",
    "gene_APLNR",
    "gene_PRG2",
    "gene_SLC43A3",
    "gene_SERPING1",
    "gene_BTBD18",
    "gene_OR9Q1",
    "gene_OR6Q1",
    "gene_OR9I1",
    "gene_OR9Q2",
    "gene_OR1S2",
    "gene_OR1S1",
    "gene_OR10Q1",
    "gene_OR10W1",
    "gene_OR5B17",
    "gene_OR5B3",
    "gene_OR5B2",
    "gene_GLYATL1",
    "gene_GLYATL1B",
    "gene_MPEG1",
    "gene_OR5AN1",
    "gene_OR5A2",
    "gene_OR4D6",
    "gene_OR4D10",
    "gene_OR4D11",
    "gene_OR4D9",
    "gene_OR10V1",
    "gene_STX3",
    "gene_OOSP4A",
    "gene_OOSP4B",
    "gene_MS4A2",
    "gene_MS4A6A",
    "gene_MS4A6E",
    "gene_MS4A7",
    "gene_MS4A1",
    "gene_MS4A8",
    "gene_MS4A18",
    "gene_MS4A15",
    "gene_MS4A10",
    "gene_CCDC86",
    "gene_PTGDR2",
    "gene_CD6",
    "gene_CD5",
    "gene_TMEM138",
    "gene_SYT7",
    "gene_MYRF",
    "gene_FEN1",
    "gene_FADS1",
    "gene_BEST1",
    "gene_SCGB1D1",
    "gene_SCGB2A2",
    "gene_SCGB1D4",
    "gene_SCGB1A1",
    "gene_ROM1",
    "gene_B3GAT3",
    "gene_GANAB",
    "gene_UQCC3",
    "gene_BSCL2",
    "gene_GNG3",
    "gene_TMEM223",
    "gene_STX5",
    "gene_TEX54",
    "gene_SLC22A8",
    "gene_SLC22A24",
    "gene_SLC22A25",
    "gene_LGALS12",
    "gene_PLAAT4",
    "gene_PLAAT2",
    "gene_C11orf95",
    "gene_SPINDOC",
    "gene_DNAJC4",
    "gene_PPP1R14B",
    "gene_PLCB3",
    "gene_KCNK4",
    "gene_CATSPERZ",
    "gene_ESRRA",
    "gene_CCDC88B",
    "gene_SLC22A11",
    "gene_SLC22A12",
    "gene_GPHA2",
    "gene_BATF2",
    "gene_ARL2",
    "gene_SAC3D1",
    "gene_TMEM262",
    "gene_VPS51",
    "gene_ZNHIT2",
    "gene_SPDYC",
    "gene_CDC42EP2",
    "gene_ZNRD2",
    "gene_EHBP1L1",
    "gene_KCNK7",
    "gene_FOSL1",
    "gene_TSGA10IP",
    "gene_EIF1AD",
    "gene_BANF1",
    "gene_CST6",
    "gene_GAL3ST3",
    "gene_PACS1",
    "gene_CD248",
    "gene_PELI3",
    "gene_ACTN3",
    "gene_C11orf86",
    "gene_RHOD",
    "gene_RAD9A",
    "gene_CARNS1",
    "gene_CORO1B",
    "gene_GPR152",
    "gene_CDK2AP2",
    "gene_TBX10",
    "gene_UNC93B1",
    "gene_CHKA",
    "gene_MRGPRD",
    "gene_SMIM38",
    "gene_MYEOV",
    "gene_FGF19",
    "gene_FGF4",
    "gene_FGF3",
    "gene_CTTN",
    "gene_KRTAP5-9",
    "gene_DEFB108B",
    "gene_LRTOMT",
    "gene_FOLR2",
    "gene_P2RY2",
    "gene_PAAF1",
    "gene_KCNE3",
    "gene_LIPT2",
    "gene_POLD3",
    "gene_OR2AT4",
    "gene_SLCO2B1",
    "gene_SERPINH1",
    "gene_MOGAT2",
    "gene_THAP12",
    "gene_GVQW3",
    "gene_EMSY",
    "gene_LRRC32",
    "gene_GDPD4",
    "gene_INTS4",
    "gene_THRSP",
    "gene_GAB2",
    "gene_FAM181B",
    "gene_PRSS23",
    "gene_FZD4",
    "gene_RAB38",
    "gene_CTSC",
    "gene_TYR",
    "gene_TRIM64B",
    "gene_MTNR1B",
    "gene_DEUP1",
    "gene_CEP295",
    "gene_HEPHL1",
    "gene_IZUMO1R",
    "gene_ANKRD49",
    "gene_C11orf97",
    "gene_FUT4",
    "gene_KDM4D",
    "gene_JRKL",
    "gene_CNTN5",
    "gene_ARHGAP42",
    "gene_PGR",
    "gene_MMP20",
    "gene_MMP8",
    "gene_MMP3",
    "gene_MMP12",
    "gene_MMP13",
    "gene_DDI1",
    "gene_CASP5",
    "gene_CARD16",
    "gene_CARD18",
    "gene_POGLUT3",
    "gene_POU2AF1",
    "gene_C11orf88",
    "gene_SIK2",
    "gene_C11orf52",
    "gene_DIXDC1",
    "gene_ANKK1",
    "gene_CLDN25",
    "gene_NNMT",
    "gene_C11orf71",
    "gene_RBM7",
    "gene_NXPE1",
    "gene_NXPE4",
    "gene_ZPR1",
    "gene_APOA5",
    "gene_APOA4",
    "gene_APOC3",
    "gene_APOA1",
    "gene_TAGLN",
    "gene_SMIM35",
    "gene_MPZL3",
    "gene_CD3E",
    "gene_TREH",
    "gene_CXCR5",
    "gene_FOXR1",
    "gene_PDZD3",
    "gene_MCAM",
    "gene_RNF26",
    "gene_MFRP",
    "gene_THY1",
    "gene_TRIM29",
    "gene_UBASH3B",
    "gene_CRTAM",
    "gene_BSX",
    "gene_SCN3B",
    "gene_OR6M1",
    "gene_OR4D5",
    "gene_OR6T1",
    "gene_OR10G6",
    "gene_OR10G7",
    "gene_OR10D3",
    "gene_OR8G5",
    "gene_OR8D1",
    "gene_OR8D2",
    "gene_OR8B12",
    "gene_PANX3",
    "gene_SPA17",
    "gene_NRGN",
    "gene_VSIG2",
    "gene_HEPACAM",
    "gene_HEPN1",
    "gene_PATE3",
    "gene_PATE4",
    "gene_VSIG10L2",
    "gene_TIRAP",
    "gene_ETS1",
    "gene_KCNJ5",
    "gene_TP53AIP1",
    "gene_BARX2",
    "gene_TMEM45B",
    "gene_SNX19",
    "gene_SPATA19",
    "gene_NCAPD3",
    "gene_GLB1L2",
    "gene_CCDC77",
    "gene_NINJ2",
    "gene_DCP1B",
    "gene_TEX52",
    "gene_FOXM1",
    "gene_RHNO1",
    "gene_FGF23",
    "gene_FGF6",
    "gene_C12orf4",
    "gene_GALNT8",
    "gene_KCNA1",
    "gene_KCNA5",
    "gene_NTF3",
    "gene_VWF",
    "gene_PLEKHG6",
    "gene_SCNN1A",
    "gene_CD27",
    "gene_ING4",
    "gene_LAG3",
    "gene_CD4",
    "gene_SPSB2",
    "gene_C1S",
    "gene_C1R",
    "gene_CLSTN3",
    "gene_ACSM4",
    "gene_CD163",
    "gene_APOBEC1",
    "gene_DPPA3",
    "gene_CLEC4C",
    "gene_SLC2A14",
    "gene_SLC2A3",
    "gene_ZNF705A",
    "gene_FAM90A1",
    "gene_AICDA",
    "gene_M6PR",
    "gene_CD69",
    "gene_CLEC2B",
    "gene_KLRF2",
    "gene_CLEC2A",
    "gene_CLEC12B",
    "gene_OLR1",
    "gene_KLRC1",
    "gene_MAGOHB",
    "gene_YBX3",
    "gene_TAS2R9",
    "gene_SMIM10L1",
    "gene_PRB3",
    "gene_APOLD1",
    "gene_GPRC5D",
    "gene_GSG1",
    "gene_EMP1",
    "gene_GUCY2C",
    "gene_SMCO3",
    "gene_ART4",
    "gene_MGP",
    "gene_PDE6H",
    "gene_RERG",
    "gene_SLC15A5",
    "gene_MGST1",
    "gene_PIK3C2G",
    "gene_PLCZ1",
    "gene_CAPZA3",
    "gene_SLCO1B3",
    "gene_SLCO1B1",
    "gene_SLCO1A2",
    "gene_IAPP",
    "gene_GYS2",
    "gene_CMAS",
    "gene_ST8SIA1",
    "gene_SSPN",
    "gene_ARNTL2",
    "gene_REP15",
    "gene_MANSC4",
    "gene_TSPAN11",
    "gene_DDX11",
    "gene_SINHCAF",
    "gene_H3F3C",
    "gene_C12orf40",
    "gene_TWF1",
    "gene_NELL2",
    "gene_SLC38A4",
    "gene_AMIGO2",
    "gene_RPAP3",
    "gene_COL2A1",
    "gene_CCDC184",
    "gene_OR10AD1",
    "gene_H1FNT",
    "gene_OR8S1",
    "gene_OR5BS1P",
    "gene_TEX49",
    "gene_TUBA1C",
    "gene_TROAP",
    "gene_C1QL4",
    "gene_FAM186B",
    "gene_FAIM2",
    "gene_AQP2",
    "gene_AQP5",
    "gene_AQP6",
    "gene_FAM186A",
    "gene_METTL7A",
    "gene_HIGD1C",
    "gene_SMAGP",
    "gene_C12orf81",
    "gene_FIGNL2",
    "gene_ANKRD33",
    "gene_NR4A1",
    "gene_SMIM41",
    "gene_KRT80",
    "gene_KRT7",
    "gene_KRT83",
    "gene_KRT84",
    "gene_KRT82",
    "gene_KRT6B",
    "gene_KRT6C",
    "gene_KRT6A",
    "gene_KRT71",
    "gene_KRT74",
    "gene_KRT72",
    "gene_KRT73",
    "gene_KRT77",
    "gene_KRT76",
    "gene_KRT3",
    "gene_KRT78",
    "gene_KRT8",
    "gene_TNS2",
    "gene_SOAT2",
    "gene_AC021072.1",
    "gene_SP7",
    "gene_AMHR2",
    "gene_HOXC13",
    "gene_HOXC12",
    "gene_HOXC11",
    "gene_HOXC10",
    "gene_HOXC6",
    "gene_HOXC8",
    "gene_HOXC5",
    "gene_NFE2",
    "gene_COPZ1",
    "gene_GPR84",
    "gene_LACRT",
    "gene_MUCL1",
    "gene_OR9K2",
    "gene_OR10A7",
    "gene_OR6C74",
    "gene_OR6C6",
    "gene_OR6C1",
    "gene_OR6C3",
    "gene_OR6C75",
    "gene_OR6C65",
    "gene_OR6C76",
    "gene_OR6C2",
    "gene_OR6C68",
    "gene_OR6C4",
    "gene_OR2AP1",
    "gene_OR10P1",
    "gene_METTL7B",
    "gene_ORMDL2",
    "gene_PYM1",
    "gene_PMEL",
    "gene_PA2G4",
    "gene_IL23A",
    "gene_APOF",
    "gene_TIMELESS",
    "gene_MIP",
    "gene_SDR9C7",
    "gene_GPR182",
    "gene_ZBTB39",
    "gene_TAC3",
    "gene_MYO1A",
    "gene_STAT6",
    "gene_NXPH4",
    "gene_NDUFA4L2",
    "gene_INHBC",
    "gene_DDIT3",
    "gene_KIF5A",
    "gene_MARCH9",
    "gene_EEF1AKMT3",
    "gene_ATP23",
    "gene_AVPR1A",
    "gene_C12orf66",
    "gene_C12orf56",
    "gene_RASSF3",
    "gene_IRAK3",
    "gene_CAND1",
    "gene_DYRK2",
    "gene_IFNG",
    "gene_IL26",
    "gene_IL22",
    "gene_MDM1",
    "gene_NUP107",
    "gene_SLC35E3",
    "gene_MDM2",
    "gene_LYZ",
    "gene_YEATS4",
    "gene_LRRC10",
    "gene_BEST3",
    "gene_MYRFL",
    "gene_KCNMB4",
    "gene_THAP2",
    "gene_GLIPR1L2",
    "gene_SYT1",
    "gene_MYF5",
    "gene_METTL25",
    "gene_TMTC2",
    "gene_SLC6A15",
    "gene_LRRIQ1",
    "gene_ALX1",
    "gene_NTS",
    "gene_C12orf50",
    "gene_KITLG",
    "gene_GALNT4",
    "gene_EPYC",
    "gene_LUM",
    "gene_DCN",
    "gene_CLLU1OS",
    "gene_C12orf74",
    "gene_SOCS2",
    "gene_CCDC38",
    "gene_ELK3",
    "gene_IKBIP",
    "gene_DEPDC4",
    "gene_NR1H4",
    "gene_GAS2L3",
    "gene_ANO4",
    "gene_SPIC",
    "gene_SYCP3",
    "gene_DRAM1",
    "gene_ASCL1",
    "gene_C12orf42",
    "gene_TDG",
    "gene_GLT8D2",
    "gene_EID3",
    "gene_C12orf75",
    "gene_CKAP4",
    "gene_RFX4",
    "gene_BTBD11",
    "gene_ASCL4",
    "gene_CMKLR1",
    "gene_FICD",
    "gene_SART3",
    "gene_DAO",
    "gene_ANAPC7",
    "gene_CCDC63",
    "gene_MYL2",
    "gene_ACAD10",
    "gene_TMEM116",
    "gene_OAS3",
    "gene_SLC8B1",
    "gene_C12orf49",
    "gene_HRK",
    "gene_RAB35",
    "gene_GCN1",
    "gene_PLA2G1B",
    "gene_TRIAP1",
    "gene_DYNLL1",
    "gene_CABP1",
    "gene_KDM2B",
    "gene_HPD",
    "gene_IL31",
    "gene_HCAR3",
    "gene_HCAR1",
    "gene_HIP1R",
    "gene_ARL6IP4",
    "gene_CDK2AP1",
    "gene_KMT5A",
    "gene_DNAH10",
    "gene_RFLNA",
    "gene_TMEM132D",
    "gene_FZD10",
    "gene_PIWIL1",
    "gene_LRCOL1",
    "gene_ZNF268",
    "gene_ANHX",
    "gene_TUBA3C",
    "gene_MPHOSPH8",
    "gene_PSPC1",
    "gene_GJA3",
    "gene_LATS2",
    "gene_SGCG",
    "gene_TNFRSF19",
    "gene_C1QTNF9",
    "gene_ATP12A",
    "gene_RNF17",
    "gene_PABPC3",
    "gene_AMER2",
    "gene_USP12",
    "gene_GSX1",
    "gene_PDX1",
    "gene_URAD",
    "gene_FLT1",
    "gene_SLC46A3",
    "gene_UBE2L5",
    "gene_ALOX5AP",
    "gene_TEX26",
    "gene_STARD13",
    "gene_NBEA",
    "gene_SOHLH2",
    "gene_SMAD9",
    "gene_CSNK1A1L",
    "gene_POSTN",
    "gene_STOML3",
    "gene_SMIM2",
    "gene_CPB2",
    "gene_LCP1",
    "gene_MLNR",
    "gene_DHRS12",
    "gene_AL445238.1",
    "gene_SLAIN1",
    "gene_SOX21",
    "gene_MBNL2",
    "gene_NALCN",
    "gene_METTL21C",
    "gene_CCDC168",
    "gene_DAOA",
    "gene_ABHD13",
    "gene_TNFSF13B",
    "gene_COL4A1",
    "gene_COL4A2",
    "gene_RAB20",
    "gene_SOX1",
    "gene_F7",
    "gene_F10",
    "gene_PROZ",
    "gene_TFDP1",
    "gene_GRK1",
    "gene_TMEM255B",
    "gene_CFAP97D2",
    "gene_POTEM",
    "gene_OR4Q3",
    "gene_OR4K2",
    "gene_OR4K5",
    "gene_OR4K1",
    "gene_OR4K15",
    "gene_OR4K14",
    "gene_OR4K13",
    "gene_OR4K17",
    "gene_OR11G2",
    "gene_OR11H6",
    "gene_OR11H4",
    "gene_RNASE10",
    "gene_RNASE11",
    "gene_RNASE12",
    "gene_EDDM3A",
    "gene_EDDM3B",
    "gene_RNASE1",
    "gene_RNASE2",
    "gene_SLC39A2",
    "gene_RNASE13",
    "gene_RNASE7",
    "gene_RNASE8",
    "gene_OR5AU1",
    "gene_OR10G3",
    "gene_OR4E2",
    "gene_OR6J1",
    "gene_MMP14",
    "gene_REM2",
    "gene_CEBPE",
    "gene_RNF212B",
    "gene_PPP1R3E",
    "gene_CMTM5",
    "gene_JPH4",
    "gene_DHRS4",
    "gene_CPNE6",
    "gene_NRL",
    "gene_FITM1",
    "gene_PSME2",
    "gene_TSSK4",
    "gene_CMA1",
    "gene_CTSG",
    "gene_GZMB",
    "gene_AP4S1",
    "gene_GPR33",
    "gene_EGLN3",
    "gene_SNX6",
    "gene_FAM177A1",
    "gene_NFKBIA",
    "gene_SFTA3",
    "gene_PAX9",
    "gene_FOXA1",
    "gene_CLEC14A",
    "gene_TRAPPC6B",
    "gene_MIA2",
    "gene_FBXO33",
    "gene_FSCB",
    "gene_FANCM",
    "gene_MGAT2",
    "gene_DNAAF2",
    "gene_POLE2",
    "gene_ARF6",
    "gene_VCPKMT",
    "gene_L2HGDH",
    "gene_PYGL",
    "gene_GNG2",
    "gene_PTGER2",
    "gene_ERO1A",
    "gene_STYX",
    "gene_GCH1",
    "gene_SOCS4",
    "gene_LGALS3",
    "gene_OTX2",
    "gene_EXOC5",
    "gene_SLC35F4",
    "gene_ARID4A",
    "gene_DACT1",
    "gene_GPR135",
    "gene_RTN1",
    "gene_PCNX4",
    "gene_C14orf39",
    "gene_SIX1",
    "gene_KCNH5",
    "gene_GPHB5",
    "gene_WDR89",
    "gene_SYNE2",
    "gene_HSPA2",
    "gene_FUT8",
    "gene_FAM71D",
    "gene_PLEKHH1",
    "gene_PIGH",
    "gene_ARG2",
    "gene_RDH12",
    "gene_GALNT16",
    "gene_PLEKHD1",
    "gene_SRSF5",
    "gene_SLC10A1",
    "gene_DCAF4",
    "gene_RIOX1",
    "gene_ACOT4",
    "gene_ACOT6",
    "gene_PNMA1",
    "gene_ZNF410",
    "gene_ENTPD5",
    "gene_VRTN",
    "gene_ISCA2",
    "gene_LTBP2",
    "gene_PROX2",
    "gene_PGF",
    "gene_EIF2B2",
    "gene_ERG28",
    "gene_SNW1",
    "gene_CEP128",
    "gene_CCDC88C",
    "gene_RIN3",
    "gene_CHGA",
    "gene_GON7",
    "gene_PRIMA1",
    "gene_FAM181A",
    "gene_IFI27L1",
    "gene_SERPINA10",
    "gene_SERPINA6",
    "gene_SERPINA9",
    "gene_SERPINA12",
    "gene_SERPINA3",
    "gene_SYNE3",
    "gene_TCL1A",
    "gene_BCL11B",
    "gene_SLC25A47",
    "gene_WARS",
    "gene_DIO3",
    "gene_ANKRD9",
    "gene_LBHD2",
    "gene_EXOC3L4",
    "gene_TMEM179",
    "gene_ADSSL1",
    "gene_SIVA1",
    "gene_ZBTB42",
    "gene_AHNAK2",
    "gene_GPR132",
    "gene_CRIP1",
    "gene_TEDC1",
    "gene_TMEM121",
    "gene_IGHE",
    "gene_IGHA1",
    "gene_IGHG1",
    "gene_IGHG3",
    "gene_IGHD",
    "gene_IGHM",
    "gene_FAM30A",
    "gene_GABRB3",
    "gene_GOLGA8M",
    "gene_CHRFAM7A",
    "gene_AC091057.6",
    "gene_GOLGA8O",
    "gene_FMN1",
    "gene_CHRM5",
    "gene_NANOGP8",
    "gene_C15orf41",
    "gene_LINC02694",
    "gene_THBS1",
    "gene_ANKRD63",
    "gene_INAFM2",
    "gene_PHGR1",
    "gene_DISP2",
    "gene_CHST14",
    "gene_GCHFR",
    "gene_C15orf62",
    "gene_PPP1R14D",
    "gene_RHOV",
    "gene_CHAC1",
    "gene_EXD1",
    "gene_OIP5",
    "gene_NUSAP1",
    "gene_ITPKA",
    "gene_PLA2G4D",
    "gene_PLA2G4F",
    "gene_CAPN3",
    "gene_EPB42",
    "gene_TGM5",
    "gene_LCMT2",
    "gene_TP53BP1",
    "gene_STRC",
    "gene_EIF3J",
    "gene_SPG11",
    "gene_TERB2",
    "gene_SLC28A2",
    "gene_SPATA5L1",
    "gene_SLC12A1",
    "gene_FBN1",
    "gene_FGF7",
    "gene_DTWD1",
    "gene_HDC",
    "gene_GABPB1",
    "gene_TNFAIP8L3",
    "gene_GLDN",
    "gene_SCG3",
    "gene_TMOD2",
    "gene_MAPK6",
    "gene_WDR72",
    "gene_UNC13C",
    "gene_PIGB",
    "gene_TEX9",
    "gene_MNS1",
    "gene_MYZAP",
    "gene_LDHAL6B",
    "gene_GCNT3",
    "gene_FOXB1",
    "gene_C2CD4A",
    "gene_C2CD4B",
    "gene_CA12",
    "gene_FBXL22",
    "gene_DAPK2",
    "gene_CIAO2A",
    "gene_PCLAF",
    "gene_PLEKHO2",
    "gene_SLC51B",
    "gene_KBTBD13",
    "gene_INTS14",
    "gene_SMAD6",
    "gene_CALML4",
    "gene_FEM1B",
    "gene_CORO2B",
    "gene_ANP32A",
    "gene_UACA",
    "gene_LARP6",
    "gene_THSD4",
    "gene_CT62",
    "gene_HEXA",
    "gene_TMEM202",
    "gene_HIGD2B",
    "gene_HCN4",
    "gene_REC114",
    "gene_ISLR2",
    "gene_STRA6",
    "gene_CCDC33",
    "gene_ARID3B",
    "gene_CYP1A1",
    "gene_CYP1A2",
    "gene_ULK3",
    "gene_ODF3L1",
    "gene_LINGO1",
    "gene_SH2D7",
    "gene_DNAJA4",
    "gene_CRABP1",
    "gene_CHRNA3",
    "gene_CHRNB4",
    "gene_BCL2A1",
    "gene_SAXO2",
    "gene_FSD2",
    "gene_RAMAC",
    "gene_C15orf40",
    "gene_ZSCAN2",
    "gene_NMB",
    "gene_SLC28A1",
    "gene_AKAP13",
    "gene_AGBL1",
    "gene_NTRK3",
    "gene_ISG20",
    "gene_RLBP1",
    "gene_PEX11A",
    "gene_WDR93",
    "gene_MESP2",
    "gene_TTLL13P",
    "gene_IQGAP1",
    "gene_HDDC3",
    "gene_UNC45A",
    "gene_PRC1",
    "gene_SV2B",
    "gene_ST8SIA2",
    "gene_SPATA8",
    "gene_ARRDC4",
    "gene_FAM169B",
    "gene_LRRC28",
    "gene_LYSMD4",
    "gene_CERS3",
    "gene_SNRPA1",
    "gene_PCSK6",
    "gene_TARSL2",
    "gene_OR4F6",
    "gene_OR4F15",
    "gene_OR4F4",
    "gene_HBA2",
    "gene_ARHGDIG",
    "gene_TMEM8A",
    "gene_PRR35",
    "gene_NHLRC4",
    "gene_RHBDL1",
    "gene_FBXL16",
    "gene_CIAO3",
    "gene_MSLNL",
    "gene_RPUSD1",
    "gene_SSTR5",
    "gene_CACNA1H",
    "gene_TPSG1",
    "gene_C16orf91",
    "gene_AL032819.3",
    "gene_PTX4",
    "gene_TMEM204",
    "gene_JPT2",
    "gene_IGFALS",
    "gene_MEIOB",
    "gene_HS3ST6",
    "gene_RNF151",
    "gene_NOXO1",
    "gene_GFER",
    "gene_SLC9A3R2",
    "gene_BRICD5",
    "gene_NTN3",
    "gene_CEMP1",
    "gene_PRSS41",
    "gene_PRSS21",
    "gene_ZG16B",
    "gene_KREMEN2",
    "gene_PAQR4",
    "gene_CLDN9",
    "gene_CLDN6",
    "gene_TNFRSF12A",
    "gene_BICDL2",
    "gene_MMP25",
    "gene_IL32",
    "gene_ZNF205",
    "gene_ZNF263",
    "gene_ZNF174",
    "gene_C16orf90",
    "gene_NLRC3",
    "gene_DNASE1",
    "gene_CREBBP",
    "gene_NMRAL1",
    "gene_ANKS3",
    "gene_SMIM22",
    "gene_SEC14L5",
    "gene_EEF2KMT",
    "gene_TMEM114",
    "gene_TMEM186",
    "gene_CARHSP1",
    "gene_LITAFD",
    "gene_CIITA",
    "gene_RMI2",
    "gene_SOCS1",
    "gene_TNP2",
    "gene_PRM3",
    "gene_PRM2",
    "gene_PRM1",
    "gene_TNFRSF17",
    "gene_PLA2G10",
    "gene_MPV17L",
    "gene_MARF1",
    "gene_MYH11",
    "gene_KNOP1",
    "gene_GPR139",
    "gene_GP2",
    "gene_ACSM2B",
    "gene_ACSM1",
    "gene_DCUN1D3",
    "gene_DNAH3",
    "gene_ANKS4B",
    "gene_CRYM",
    "gene_OTOA",
    "gene_PDZD9",
    "gene_VWA3A",
    "gene_SCNN1G",
    "gene_COG7",
    "gene_PRKCB",
    "gene_RBBP6",
    "gene_AQP8",
    "gene_APOBR",
    "gene_IL27",
    "gene_NUPR1",
    "gene_ATP2A1",
    "gene_CD19",
    "gene_ZG16",
    "gene_PAGR1",
    "gene_C16orf92",
    "gene_ZNF771",
    "gene_SEPHS2",
    "gene_ZNF747",
    "gene_ZNF785",
    "gene_ZNF689",
    "gene_ORAI3",
    "gene_STX1B",
    "gene_VKORC1",
    "gene_PRSS8",
    "gene_PYCARD",
    "gene_TRIM72",
    "gene_ITGAX",
    "gene_COX6A2",
    "gene_ARMC5",
    "gene_AHSP",
    "gene_MYLK3",
    "gene_GPT2",
    "gene_ABCC12",
    "gene_ABCC11",
    "gene_SIAH1",
    "gene_C16orf78",
    "gene_IRX5",
    "gene_MMP2",
    "gene_SLC6A2",
    "gene_MT2A",
    "gene_MT1X",
    "gene_SLC12A3",
    "gene_PLLP",
    "gene_CCL22",
    "gene_CCL17",
    "gene_ADGRG3",
    "gene_CSNK2A2",
    "gene_PRSS54",
    "gene_GINS3",
    "gene_NDRG4",
    "gene_CDH5",
    "gene_BEAN1",
    "gene_CKLF",
    "gene_TERB1",
    "gene_PDP2",
    "gene_CDH16",
    "gene_B3GNT9",
    "gene_TRADD",
    "gene_NOL3",
    "gene_EXOC3L1",
    "gene_TPPP3",
    "gene_AGRP",
    "gene_LCAT",
    "gene_DPEP3",
    "gene_DPEP2NB",
    "gene_HAS3",
    "gene_PDF",
    "gene_TMED6",
    "gene_NQO1",
    "gene_WWP2",
    "gene_CLEC18C",
    "gene_COG4",
    "gene_CALB2",
    "gene_ZNF19",
    "gene_CHST4",
    "gene_TAT",
    "gene_MARVELD3",
    "gene_HP",
    "gene_MLKL",
    "gene_FA2H",
    "gene_CTRB2",
    "gene_CTRB1",
    "gene_TMEM170A",
    "gene_TMEM231",
    "gene_AC025287.4",
    "gene_CPHXL",
    "gene_CNTNAP4",
    "gene_ADAMTS18",
    "gene_NUDT7",
    "gene_CLEC3A",
    "gene_DYNLRB2",
    "gene_C16orf46",
    "gene_SDR42E1",
    "gene_MPHOSPH6",
    "gene_CDH13",
    "gene_OSGIN1",
    "gene_NECAB2",
    "gene_WFDC1",
    "gene_CRISPLD2",
    "gene_GINS2",
    "gene_C16orf74",
    "gene_COX4I1",
    "gene_IRF8",
    "gene_FOXF1",
    "gene_KLHDC4",
    "gene_SLC7A5",
    "gene_CA5A",
    "gene_ZNF469",
    "gene_IL17C",
    "gene_CYBA",
    "gene_MVD",
    "gene_GALNS",
    "gene_PABPN1L",
    "gene_SPATA33",
    "gene_SPATA2L",
    "gene_CENPBD1",
    "gene_PRDM7",
    "gene_C17orf97",
    "gene_VPS53",
    "gene_GEMIN4",
    "gene_NXN",
    "gene_BHLHA9",
    "gene_TRARG1",
    "gene_SCARF1",
    "gene_TSR1",
    "gene_OR1D5",
    "gene_OR1D2",
    "gene_OR1G1",
    "gene_OR1A2",
    "gene_OR1A1",
    "gene_OR3A2",
    "gene_OR3A1",
    "gene_AC087498.1",
    "gene_OR1E1",
    "gene_OR3A3",
    "gene_ASPA",
    "gene_CTNS",
    "gene_EMC6",
    "gene_HASPIN",
    "gene_ALOX15",
    "gene_MED11",
    "gene_TM4SF5",
    "gene_GLTPD2",
    "gene_CHRNE",
    "gene_ENO3",
    "gene_SLC52A1",
    "gene_USP6",
    "gene_WSCD1",
    "gene_AIPL1",
    "gene_FBXO39",
    "gene_ALOX12",
    "gene_TMEM95",
    "gene_SPEM2",
    "gene_CHRNB1",
    "gene_POLR2A",
    "gene_TNFSF13",
    "gene_CD68",
    "gene_MPDU1",
    "gene_SOX15",
    "gene_TMEM88",
    "gene_RNF227",
    "gene_TRAPPC1",
    "gene_CNTROB",
    "gene_ALOX12B",
    "gene_ALOXE3",
    "gene_BORCS6",
    "gene_ODF4",
    "gene_CCDC42",
    "gene_SPDYE4",
    "gene_MFSD6L",
    "gene_DHRS7C",
    "gene_MYH1",
    "gene_SCO1",
    "gene_PIRT",
    "gene_DNAH9",
    "gene_ZNF18",
    "gene_CDRT15",
    "gene_CDRT1",
    "gene_TNFRSF13B",
    "gene_PLD6",
    "gene_SREBF1",
    "gene_SHMT1",
    "gene_TBC1D28",
    "gene_FBXW10",
    "gene_SLC5A10",
    "gene_MAPK7",
    "gene_SLC47A2",
    "gene_ALDH3A1",
    "gene_USP22",
    "gene_MAP2K3",
    "gene_LINC02693",
    "gene_KSR1",
    "gene_LGALS9",
    "gene_NLK",
    "gene_TMEM97",
    "gene_SEBOX",
    "gene_RAB34",
    "gene_TIAF1",
    "gene_ABHD15",
    "gene_TMIGD1",
    "gene_CRLF3",
    "gene_ATAD5",
    "gene_ADAP2",
    "gene_EVI2A",
    "gene_CDK5R1",
    "gene_SPACA3",
    "gene_CCL2",
    "gene_CCL7",
    "gene_CCL11",
    "gene_CCL13",
    "gene_CCL1",
    "gene_FNDC8",
    "gene_UNC45B",
    "gene_SLFN11",
    "gene_SLFN14",
    "gene_GAS2L2",
    "gene_C17orf50",
    "gene_HEATR9",
    "gene_RDM1",
    "gene_LYZL6",
    "gene_CCL15",
    "gene_CCL23",
    "gene_CCL3",
    "gene_CCL4",
    "gene_TBC1D3B",
    "gene_MRM1",
    "gene_LHX1",
    "gene_C17orf78",
    "gene_HNF1B",
    "gene_TBC1D3E",
    "gene_ARHGAP23",
    "gene_FBXO47",
    "gene_PNMT",
    "gene_GRB7",
    "gene_LRRC3C",
    "gene_GJD3",
    "gene_TOP2A",
    "gene_IGFBP4",
    "gene_CCR7",
    "gene_SMARCE1",
    "gene_KRT24",
    "gene_KRT25",
    "gene_KRT26",
    "gene_TMEM99",
    "gene_KRT12",
    "gene_KRT39",
    "gene_KRT40",
    "gene_KRTAP3-3",
    "gene_KRTAP3-2",
    "gene_KRTAP1-5",
    "gene_KRTAP1-1",
    "gene_KRTAP2-3",
    "gene_KRTAP2-4",
    "gene_KRTAP4-12",
    "gene_KRTAP4-6",
    "gene_KRTAP4-5",
    "gene_KRTAP4-4",
    "gene_KRTAP4-3",
    "gene_KRTAP4-2",
    "gene_KRTAP9-3",
    "gene_KRTAP9-8",
    "gene_KRTAP9-9",
    "gene_KRTAP9-6",
    "gene_KRTAP9-7",
    "gene_KRTAP16-1",
    "gene_KRT33A",
    "gene_KRT33B",
    "gene_KRT34",
    "gene_KRT31",
    "gene_KRT37",
    "gene_KRT38",
    "gene_KRT32",
    "gene_KRT13",
    "gene_KRT15",
    "gene_KRT19",
    "gene_KRT9",
    "gene_GAST",
    "gene_FKBP10",
    "gene_KLHL10",
    "gene_CNP",
    "gene_ZNF385C",
    "gene_KAT2A",
    "gene_HSPB9",
    "gene_KCNH4",
    "gene_CAVIN1",
    "gene_NAGLU",
    "gene_PSMC3IP",
    "gene_WNK4",
    "gene_AOC3",
    "gene_G6PC",
    "gene_IFI35",
    "gene_BRCA1",
    "gene_CCDC200",
    "gene_ARL4D",
    "gene_DHX8",
    "gene_MEOX1",
    "gene_SOST",
    "gene_CD300LG",
    "gene_PYY",
    "gene_TMEM101",
    "gene_G6PC3",
    "gene_ASB16",
    "gene_ATXN7L3",
    "gene_UBTF",
    "gene_SLC4A1",
    "gene_RUNDC3A",
    "gene_GRN",
    "gene_FZD2",
    "gene_MEIOC",
    "gene_DBF4B",
    "gene_HIGD1B",
    "gene_EFTUD2",
    "gene_SPATA32",
    "gene_ARHGAP27",
    "gene_STH",
    "gene_NSF",
    "gene_WNT9B",
    "gene_MYL4",
    "gene_TBX21",
    "gene_SP6",
    "gene_PNPO",
    "gene_PRR15L",
    "gene_HOXB1",
    "gene_HOXB2",
    "gene_HOXB3",
    "gene_HOXB5",
    "gene_HOXB6",
    "gene_HOXB7",
    "gene_HOXB8",
    "gene_HOXB9",
    "gene_PRAC2",
    "gene_B4GALNT2",
    "gene_PHOSPHO1",
    "gene_PHB",
    "gene_TAC4",
    "gene_DLX4",
    "gene_SAMD14",
    "gene_SGCA",
    "gene_COL1A1",
    "gene_TMEM92",
    "gene_LRRC59",
    "gene_CHAD",
    "gene_EPN3",
    "gene_ABCC3",
    "gene_ANKRD40CL",
    "gene_KIF2B",
    "gene_SMIM36",
    "gene_C17orf67",
    "gene_COIL",
    "gene_CCDC182",
    "gene_CUEDC1",
    "gene_OR4D2",
    "gene_EPX",
    "gene_HSF5",
    "gene_AC011195.2",
    "gene_SMG8",
    "gene_TUBD1",
    "gene_RNFT1",
    "gene_C17orf64",
    "gene_PPM1D",
    "gene_EFCAB3",
    "gene_MRC2",
    "gene_MARCH10",
    "gene_ACE",
    "gene_KCNH6",
    "gene_CSH2",
    "gene_CSHL1",
    "gene_GH1",
    "gene_SCN4A",
    "gene_ERN1",
    "gene_PECAM1",
    "gene_LRRC37A3",
    "gene_APOH",
    "gene_HELZ",
    "gene_AMZ2",
    "gene_FAM20A",
    "gene_ABCA8",
    "gene_SLC39A11",
    "gene_C17orf80",
    "gene_TTYH2",
    "gene_DNAI2",
    "gene_GPR142",
    "gene_TMEM104",
    "gene_USH1G",
    "gene_OTOP3",
    "gene_SUMO2",
    "gene_MIF4GD",
    "gene_MYO15B",
    "gene_SMIM5",
    "gene_SMIM6",
    "gene_ITGB4",
    "gene_EVPL",
    "gene_ZACN",
    "gene_GALR2",
    "gene_FOXJ1",
    "gene_AANAT",
    "gene_METTL23",
    "gene_C17orf99",
    "gene_BIRC5",
    "gene_TMEM235",
    "gene_SOCS3",
    "gene_CEP295NL",
    "gene_LGALS3BP",
    "gene_C1QTNF1",
    "gene_ENGASE",
    "gene_ENPP7",
    "gene_CBX8",
    "gene_CARD14",
    "gene_ENDOV",
    "gene_NPTX1",
    "gene_AATK",
    "gene_PVALEF",
    "gene_CEP131",
    "gene_PDE6G",
    "gene_CCDC137",
    "gene_PPP1R27",
    "gene_P4HB",
    "gene_NPB",
    "gene_MYADML2",
    "gene_CCDC57",
    "gene_SLC16A3",
    "gene_CD7",
    "gene_SECTM1",
    "gene_TEX19",
    "gene_ZNF750",
    "gene_METRNL",
    "gene_CETN1",
    "gene_EMILIN2",
    "gene_TGIF1",
    "gene_DLGAP1",
    "gene_ZBTB14",
    "gene_LRRC30",
    "gene_MTCL1",
    "gene_RALBP1",
    "gene_GNAL",
    "gene_IMPA2",
    "gene_ZNF519",
    "gene_GATA6",
    "gene_CTAGE1",
    "gene_ANKRD29",
    "gene_HRH4",
    "gene_PSMA8",
    "gene_DSG4",
    "gene_DSG3",
    "gene_TTR",
    "gene_KLHL14",
    "gene_CCDC178",
    "gene_INO80C",
    "gene_C18orf21",
    "gene_KIAA1328",
    "gene_SIGLEC15",
    "gene_LOXHD1",
    "gene_KATNAL2",
    "gene_ELOA3",
    "gene_ELOA2",
    "gene_SKOR2",
    "gene_MYO5B",
    "gene_ELAC1",
    "gene_DYNAP",
    "gene_CCDC68",
    "gene_WDR7",
    "gene_BOD1L2",
    "gene_FECH",
    "gene_ALPK2",
    "gene_GRP",
    "gene_RAX",
    "gene_CPLX4",
    "gene_LMAN1",
    "gene_CCBE1",
    "gene_PMAIP1",
    "gene_SERPINB5",
    "gene_SERPINB12",
    "gene_SERPINB13",
    "gene_SERPINB11",
    "gene_SERPINB3",
    "gene_SERPINB7",
    "gene_SERPINB2",
    "gene_SERPINB10",
    "gene_CCDC102B",
    "gene_C18orf63",
    "gene_CNDP1",
    "gene_ZNF407",
    "gene_SMIM21",
    "gene_MBP",
    "gene_GALR1",
    "gene_SALL3",
    "gene_KCNG2",
    "gene_AC090360.1",
    "gene_C2CD4C",
    "gene_ODF3L2",
    "gene_MADCAM1",
    "gene_TPGS1",
    "gene_GZMM",
    "gene_PRSS57",
    "gene_MISP",
    "gene_AZU1",
    "gene_PRTN3",
    "gene_ELANE",
    "gene_GRIN3B",
    "gene_CNN2",
    "gene_SBNO2",
    "gene_EFNA2",
    "gene_GAMT",
    "gene_C19orf25",
    "gene_MEX3D",
    "gene_TCF3",
    "gene_ONECUT3",
    "gene_ADAT3",
    "gene_DOT1L",
    "gene_PLEKHJ1",
    "gene_JSRP1",
    "gene_SPPL2B",
    "gene_TIMM13",
    "gene_GADD45B",
    "gene_TLE6",
    "gene_GNA11",
    "gene_S1PR4",
    "gene_AC005551.1",
    "gene_RAX2",
    "gene_NMRK2",
    "gene_CHAF1A",
    "gene_PLIN4",
    "gene_LRG1",
    "gene_TNFAIP8L1",
    "gene_PLIN3",
    "gene_UHRF1",
    "gene_ZNRF4",
    "gene_LONP1",
    "gene_FUT3",
    "gene_VMAC",
    "gene_CAPS",
    "gene_ACSBG2",
    "gene_CRB3",
    "gene_AC119396.1",
    "gene_PEX11G",
    "gene_CAMSAP3",
    "gene_PCP2",
    "gene_STXBP2",
    "gene_CD209",
    "gene_CLEC4M",
    "gene_SNAPC2",
    "gene_KANK3",
    "gene_ANGPTL4",
    "gene_MYO1F",
    "gene_ACTL9",
    "gene_OR2Z1",
    "gene_MBD3L1",
    "gene_MUC16",
    "gene_OR1M1",
    "gene_OR7G1",
    "gene_OR7D2",
    "gene_ZNF560",
    "gene_FBXL12",
    "gene_RDH8",
    "gene_ICAM1",
    "gene_ICAM4",
    "gene_FDX2",
    "gene_ICAM3",
    "gene_S1PR5",
    "gene_TMED1",
    "gene_TIMM29",
    "gene_TSPAN16",
    "gene_CCDC159",
    "gene_ZNF441",
    "gene_ZNF763",
    "gene_ZNF433",
    "gene_ZNF442",
    "gene_GNG14",
    "gene_BEST2",
    "gene_KLF1",
    "gene_LYL1",
    "gene_STX10",
    "gene_IER2",
    "gene_RLN3",
    "gene_ADGRE5",
    "gene_DDX39A",
    "gene_PTGER1",
    "gene_DNAJB1",
    "gene_ADGRE3",
    "gene_ADGRE2",
    "gene_OR7C1",
    "gene_OR7A17",
    "gene_CCDC105",
    "gene_CASP14",
    "gene_NOTCH3",
    "gene_EPHX3",
    "gene_PGLYRP2",
    "gene_CYP4F8",
    "gene_OR10H3",
    "gene_CYP4F2",
    "gene_OR10H4",
    "gene_KLF2",
    "gene_C19orf44",
    "gene_HAUS8",
    "gene_PLVAP",
    "gene_NXNL1",
    "gene_NIBAN3",
    "gene_COLGALT1",
    "gene_INSL3",
    "gene_SLC5A5",
    "gene_IL12RB1",
    "gene_IFI30",
    "gene_RAB3A",
    "gene_GDF15",
    "gene_LRRC25",
    "gene_FKBP8",
    "gene_TMEM59L",
    "gene_KLHL26",
    "gene_COMP",
    "gene_HOMER3",
    "gene_NCAN",
    "gene_PBX4",
    "gene_ZNF682",
    "gene_ZNF98",
    "gene_ZNF492",
    "gene_ZNF99",
    "gene_ZNF723",
    "gene_ZNF730",
    "gene_PLEKHF1",
    "gene_URI1",
    "gene_ZNF536",
    "gene_TSHZ3",
    "gene_PDCD5",
    "gene_RGS9BP",
    "gene_NUDT19",
    "gene_CEP89",
    "gene_GPATCH1",
    "gene_CHST8",
    "gene_FXYD3",
    "gene_FAM187B",
    "gene_LSR",
    "gene_HAMP",
    "gene_CD22",
    "gene_FFAR2",
    "gene_KRTDAP",
    "gene_GAPDHS",
    "gene_PMIS2",
    "gene_UPK1A",
    "gene_ZBTB32",
    "gene_IGFLR1",
    "gene_HSPB6",
    "gene_PRODH2",
    "gene_NPHS1",
    "gene_KIRREL2",
    "gene_TYROBP",
    "gene_OVOL3",
    "gene_ZNF567",
    "gene_ZNF345",
    "gene_ZNF568",
    "gene_ZNF585B",
    "gene_ZNF383",
    "gene_ZNF569",
    "gene_WDR87",
    "gene_PPP1R14A",
    "gene_C19orf33",
    "gene_CATSPERG",
    "gene_SPRED3",
    "gene_LGALS4",
    "gene_SIRT2",
    "gene_FBXO17",
    "gene_NCCRP1",
    "gene_SYCN",
    "gene_IFNL1",
    "gene_GMFG",
    "gene_ZFP36",
    "gene_SELENOV",
    "gene_EID2B",
    "gene_LGALS13",
    "gene_LGALS16",
    "gene_LGALS14",
    "gene_LEUTX",
    "gene_FCGBP",
    "gene_ZNF780A",
    "gene_PLD3",
    "gene_HIPK4",
    "gene_PRX",
    "gene_SERTAD1",
    "gene_ITPKC",
    "gene_MIA",
    "gene_CYP2A6",
    "gene_CYP2A7",
    "gene_CYP2A13",
    "gene_CYP2F1",
    "gene_B3GNT8",
    "gene_CEACAM7",
    "gene_CEACAM5",
    "gene_CEACAM6",
    "gene_LYPD4",
    "gene_DMRTC2",
    "gene_ARHGEF1",
    "gene_ATP1A3",
    "gene_DEDD2",
    "gene_CIC",
    "gene_CEACAM8",
    "gene_TEX101",
    "gene_XRCC1",
    "gene_SRRM5",
    "gene_PLAUR",
    "gene_IRGC",
    "gene_KCNN4",
    "gene_ZNF234",
    "gene_ZNF227",
    "gene_ZNF285",
    "gene_ZNF229",
    "gene_ZNF180",
    "gene_PVR",
    "gene_CEACAM19",
    "gene_CEACAM16",
    "gene_BCL3",
    "gene_TOMM40",
    "gene_APOE",
    "gene_APOC1",
    "gene_APOC2",
    "gene_GEMIN7",
    "gene_BLOC1S3",
    "gene_CKM",
    "gene_FOSB",
    "gene_PPM1N",
    "gene_OPA3",
    "gene_GPR4",
    "gene_FBXO46",
    "gene_BHMG1",
    "gene_RSPH6A",
    "gene_FOXA3",
    "gene_NANOS2",
    "gene_PGLYRP1",
    "gene_IGFL3",
    "gene_IGFL1",
    "gene_CCDC8",
    "gene_PNMA8C",
    "gene_CALM3",
    "gene_PTGIR",
    "gene_BBC3",
    "gene_CCDC9",
    "gene_C5AR1",
    "gene_C5AR2",
    "gene_EHD2",
    "gene_NOP53",
    "gene_CRX",
    "gene_SULT2A1",
    "gene_ELSPBP1",
    "gene_CABP5",
    "gene_PLA2G4C",
    "gene_CCDC114",
    "gene_EMP3",
    "gene_TMEM143",
    "gene_SULT2B1",
    "gene_SPACA4",
    "gene_CA11",
    "gene_FGF21",
    "gene_PLEKHA4",
    "gene_PPP1R15A",
    "gene_LHB",
    "gene_AC008687.4",
    "gene_KCNA7",
    "gene_TRPM4",
    "gene_DKKL1",
    "gene_GFY",
    "gene_SLC17A7",
    "gene_RCN3",
    "gene_PRRG2",
    "gene_PRR12",
    "gene_IRF3",
    "gene_TSKS",
    "gene_ATF5",
    "gene_VRK3",
    "gene_ZNF473",
    "gene_IZUMO2",
    "gene_SPIB",
    "gene_CLEC11A",
    "gene_GPR32",
    "gene_KLK1",
    "gene_KLK15",
    "gene_KLK3",
    "gene_KLK4",
    "gene_KLK5",
    "gene_KLK6",
    "gene_KLK8",
    "gene_KLK9",
    "gene_KLK11",
    "gene_KLK12",
    "gene_KLK13",
    "gene_SIGLECL1",
    "gene_LIM2",
    "gene_C19orf84",
    "gene_ZNF175",
    "gene_SIGLEC5",
    "gene_FPR1",
    "gene_FPR2",
    "gene_FPR3",
    "gene_ZNF836",
    "gene_ZNF534",
    "gene_ERVV-1",
    "gene_ERVV-2",
    "gene_ZNF160",
    "gene_ZNF677",
    "gene_VN1R2",
    "gene_VN1R4",
    "gene_ZNF765",
    "gene_DPRX",
    "gene_NLRP12",
    "gene_CACNG6",
    "gene_VSTM1",
    "gene_TARM1",
    "gene_OSCAR",
    "gene_LENG1",
    "gene_TSEN34",
    "gene_LILRA6",
    "gene_LILRA4",
    "gene_LAIR1",
    "gene_LAIR2",
    "gene_LILRA1",
    "gene_KIR2DL4",
    "gene_FCAR",
    "gene_NCR1",
    "gene_NLRP7",
    "gene_EPS8L1",
    "gene_SYT5",
    "gene_COX6B2",
    "gene_FAM71E2",
    "gene_C19orf85",
    "gene_NAT14",
    "gene_SBK2",
    "gene_ZNF579",
    "gene_ZNF524",
    "gene_ZNF784",
    "gene_ZNF581",
    "gene_EPN1",
    "gene_NLRP9",
    "gene_NLRP13",
    "gene_NLRP5",
    "gene_GALP",
    "gene_ZSCAN5B",
    "gene_ZSCAN5C",
    "gene_EDDM13",
    "gene_ZIM2",
    "gene_PEG3",
    "gene_ZIM3",
    "gene_ZNF264",
    "gene_ZNF548",
    "gene_ZNF772",
    "gene_ZNF549",
    "gene_ZNF550",
    "gene_ZNF134",
    "gene_ZNF671",
    "gene_ZNF586",
    "gene_ZNF837",
    "gene_ZNF132",
    "gene_ZNF324",
    "gene_CHMP2A",
    "gene_DEFB125",
    "gene_DEFB126",
    "gene_DEFB132",
    "gene_SOX12",
    "gene_TRIB3",
    "gene_SRXN1",
    "gene_SCRT2",
    "gene_ANGPT4",
    "gene_TMEM74B",
    "gene_C20orf202",
    "gene_RAD21L1",
    "gene_SIRPB2",
    "gene_SIRPG",
    "gene_PDYN",
    "gene_TGM6",
    "gene_TMC2",
    "gene_CPXM1",
    "gene_C20orf141",
    "gene_TMEM239",
    "gene_OXT",
    "gene_AVP",
    "gene_HSPA12B",
    "gene_AP5S1",
    "gene_SMOX",
    "gene_ADRA1D",
    "gene_PRNP",
    "gene_PRND",
    "gene_SHLD1",
    "gene_CHGB",
    "gene_TRMT6",
    "gene_MCM8",
    "gene_LRRN4",
    "gene_LAMP5",
    "gene_ANKEF1",
    "gene_SNAP25",
    "gene_JAG1",
    "gene_TASP1",
    "gene_SNRPB2",
    "gene_OTOR",
    "gene_RRBP1",
    "gene_BANF2",
    "gene_SNX5",
    "gene_SMIM26",
    "gene_NAA20",
    "gene_CFAP61",
    "gene_INSM1",
    "gene_NKX2-4",
    "gene_NKX2-2",
    "gene_FOXA2",
    "gene_SSTR4",
    "gene_THBD",
    "gene_NXT1",
    "gene_NAPB",
    "gene_CSTL1",
    "gene_CST8",
    "gene_CST9L",
    "gene_GGTLC1",
    "gene_CST7",
    "gene_ACSS1",
    "gene_VSX1",
    "gene_ABHD12",
    "gene_DEFB116",
    "gene_DEFB119",
    "gene_DEFB121",
    "gene_DEFB123",
    "gene_DEFB124",
    "gene_REM1",
    "gene_ID1",
    "gene_FOXS1",
    "gene_SUN5",
    "gene_BPIFB4",
    "gene_BPIFA3",
    "gene_BPIFB1",
    "gene_ACTL10",
    "gene_MAP1LC3A",
    "gene_TP53INP2",
    "gene_FAM83C",
    "gene_GDF5OS",
    "gene_CPNE1",
    "gene_EPB41L1",
    "gene_MYL9",
    "gene_NNAT",
    "gene_VSTM2L",
    "gene_RPRD1B",
    "gene_TGM2",
    "gene_LBP",
    "gene_ADIG",
    "gene_SLC32A1",
    "gene_EMILIN3",
    "gene_PTPRT",
    "gene_GTSF1L",
    "gene_R3HDML",
    "gene_CCN5",
    "gene_PABPC1L",
    "gene_WFDC5",
    "gene_WFDC12",
    "gene_PI3",
    "gene_SEMG1",
    "gene_SEMG2",
    "gene_SLPI",
    "gene_DBNDD2",
    "gene_WFDC2",
    "gene_SPINT3",
    "gene_WFDC6",
    "gene_WFDC8",
    "gene_WFDC11",
    "gene_WFDC10B",
    "gene_WFDC13",
    "gene_SPINT4",
    "gene_WFDC3",
    "gene_UBE2C",
    "gene_NEURL2",
    "gene_PLTP",
    "gene_MMP9",
    "gene_CDH22",
    "gene_OCSTAMP",
    "gene_ZMYND8",
    "gene_PREX1",
    "gene_SNAI1",
    "gene_CEBPB",
    "gene_RIPOR3",
    "gene_PARD6B",
    "gene_MOCS3",
    "gene_ZFP64",
    "gene_CYP24A1",
    "gene_DOK5",
    "gene_MC3R",
    "gene_RTF2",
    "gene_GCNT7",
    "gene_SPO11",
    "gene_CTCFL",
    "gene_APCDD1L",
    "gene_TUBB1",
    "gene_PRELID3B",
    "gene_PPP1R3D",
    "gene_OSBPL2",
    "gene_RBBP8NL",
    "gene_GATA5",
    "gene_MRGBP",
    "gene_COL9A3",
    "gene_BHLHE23",
    "gene_BIRC7",
    "gene_EEF1A2",
    "gene_PTK6",
    "gene_SRMS",
    "gene_TNFRSF6B",
    "gene_LIME1",
    "gene_ABHD16B",
    "gene_DNAJC5",
    "gene_C20orf204",
    "gene_SOX18",
    "gene_NPBWR2",
    "gene_TPTE",
    "gene_RBM11",
    "gene_GABPA",
    "gene_CYYR1",
    "gene_ADAMTS1",
    "gene_USP16",
    "gene_CLDN17",
    "gene_CLDN8",
    "gene_KRTAP24-1",
    "gene_KRTAP25-1",
    "gene_KRTAP26-1",
    "gene_KRTAP27-1",
    "gene_KRTAP13-2",
    "gene_KRTAP13-1",
    "gene_KRTAP13-3",
    "gene_KRTAP13-4",
    "gene_KRTAP19-3",
    "gene_KRTAP19-4",
    "gene_KRTAP19-5",
    "gene_KRTAP19-7",
    "gene_KRTAP6-3",
    "gene_KRTAP22-1",
    "gene_KRTAP6-1",
    "gene_KRTAP20-1",
    "gene_KRTAP20-4",
    "gene_KRTAP20-2",
    "gene_KRTAP20-3",
    "gene_KRTAP21-2",
    "gene_KRTAP8-1",
    "gene_KRTAP7-1",
    "gene_KRTAP11-1",
    "gene_MRAP",
    "gene_OLIG1",
    "gene_DNAJC28",
    "gene_KCNE2",
    "gene_CLIC6",
    "gene_SETD4",
    "gene_CBR1",
    "gene_CBR3",
    "gene_DOP1B",
    "gene_CLDN14",
    "gene_DSCAM",
    "gene_UMODL1",
    "gene_TFF3",
    "gene_TFF2",
    "gene_HSF2BP",
    "gene_DNMT3L",
    "gene_LRRC3",
    "gene_TSPEAR",
    "gene_KRTAP10-1",
    "gene_KRTAP10-2",
    "gene_KRTAP10-7",
    "gene_KRTAP10-10",
    "gene_KRTAP10-11",
    "gene_KRTAP12-4",
    "gene_KRTAP12-3",
    "gene_KRTAP12-1",
    "gene_ITGB2",
    "gene_FAM207A",
    "gene_COL18A1",
    "gene_SLC19A1",
    "gene_COL6A1",
    "gene_COL6A2",
    "gene_CCT8L2",
    "gene_GAB4",
    "gene_ADA2",
    "gene_BID",
    "gene_TSSK2",
    "gene_CLDN5",
    "gene_CCDC188",
    "gene_SCARF2",
    "gene_THAP7",
    "gene_GGT2",
    "gene_AP000552.4",
    "gene_RIMBP3B",
    "gene_CCDC116",
    "gene_VPREB1",
    "gene_ZNF280A",
    "gene_IGLC1",
    "gene_RSPH14",
    "gene_RGL4",
    "gene_VPREB3",
    "gene_C22orf15",
    "gene_MMP11",
    "gene_DDTL",
    "gene_GSTT4",
    "gene_UPB1",
    "gene_PIWIL3",
    "gene_TMEM211",
    "gene_TPST2",
    "gene_CRYBB1",
    "gene_CRYBA4",
    "gene_CHEK2",
    "gene_CCDC117",
    "gene_LIF",
    "gene_OSM",
    "gene_RNF215",
    "gene_MORC2",
    "gene_C22orf42",
    "gene_RFPL3",
    "gene_TIMP3",
    "gene_ISX",
    "gene_HMOX1",
    "gene_APOL6",
    "gene_APOL3",
    "gene_APOL4",
    "gene_APOL1",
    "gene_MYH9",
    "gene_TEX33",
    "gene_IL2RB",
    "gene_SSTR3",
    "gene_RAC2",
    "gene_CYTH4",
    "gene_CDC42EP1",
    "gene_LGALS2",
    "gene_TRIOBP",
    "gene_GCAT",
    "gene_GALR3",
    "gene_SOX10",
    "gene_SLC16A8",
    "gene_PLA2G6",
    "gene_MAFF",
    "gene_TMEM184B",
    "gene_TOMM22",
    "gene_DNAL4",
    "gene_NPTXR",
    "gene_APOBEC3A",
    "gene_APOBEC3C",
    "gene_GRAP2",
    "gene_Z82206.1",
    "gene_ST13",
    "gene_CENPM",
    "gene_SEPTIN3",
    "gene_WBP2NL",
    "gene_NAGA",
    "gene_BIK",
    "gene_TSPO",
    "gene_SULT4A1",
    "gene_PARVG",
    "gene_FBLN1",
    "gene_ATXN10",
    "gene_PPARA",
    "gene_CDPF1",
    "gene_PKDREJ",
    "gene_CELSR1",
    "gene_CRELD2",
    "gene_PIM3",
    "gene_IL17REL",
    "gene_TTLL8",
    "gene_MOV10L1",
    "gene_TRABD",
    "gene_ADM2",
    "gene_MIOX",
    "gene_SCO2",
    "gene_ODF3B",
    "gene_CRLF2",
    "gene_CSF2RA",
    "gene_CLDN34",
    "gene_TMSB4X",
    "gene_ATXN3L",
    "gene_EGFL6",
    "gene_OFD1",
    "gene_MAGEB17",
    "gene_BEND2",
    "gene_RS1",
    "gene_MAP3K15",
    "gene_YY2",
    "gene_MAGEB18",
    "gene_MAGEB6B",
    "gene_MAGEB5",
    "gene_PPP4R3C",
    "gene_DCAF8L2",
    "gene_MAGEB10",
    "gene_MAGEB2",
    "gene_MAGEB3",
    "gene_FAM47A",
    "gene_FAM47B",
    "gene_MAGEB16",
    "gene_HYPM",
    "gene_TSPAN7",
    "gene_USP9X",
    "gene_DDX3X",
    "gene_NYX",
    "gene_GPR34",
    "gene_DUSP21",
    "gene_ARAF",
    "gene_SYN1",
    "gene_TIMP1",
    "gene_ZNF630",
    "gene_SSX3",
    "gene_FTSJ1",
    "gene_PLP2",
    "gene_SYP",
    "gene_GAGE1",
    "gene_PAGE1",
    "gene_CLCN5",
    "gene_BMP15",
    "gene_EZHIP",
    "gene_TSPYL2",
    "gene_ITIH6",
    "gene_ALAS2",
    "gene_FAM104B",
    "gene_FOXR2",
    "gene_ASB12",
    "gene_MSN",
    "gene_VSIG4",
    "gene_DGAT2L6",
    "gene_CXorf65",
    "gene_ITGB1BP2",
    "gene_CXCR3",
    "gene_BX276092.9",
    "gene_ZCCHC13",
    "gene_FGF16",
    "gene_CYSLTR1",
    "gene_GPR174",
    "gene_ITM2A",
    "gene_CYLC1",
    "gene_CPXCR1",
    "gene_TGIF2LX",
    "gene_TNMD",
    "gene_TIMM8A",
    "gene_TCP11X1",
    "gene_BEX1",
    "gene_NXF3",
    "gene_PLP1",
    "gene_NRK",
    "gene_RIPPLY1",
    "gene_COL4A5",
    "gene_GUCY2F",
    "gene_RTL9",
    "gene_CAPN6",
    "gene_SERTM2",
    "gene_RBMXL3",
    "gene_LUZP4",
    "gene_KIAA1210",
    "gene_SOWAHD",
    "gene_RHOXF2B",
    "gene_ATP1B4",
    "gene_CT47B1",
    "gene_STAG2",
    "gene_SH2D1A",
    "gene_TEX13C",
    "gene_DCAF12L2",
    "gene_DCAF12L1",
    "gene_ACTRT1",
    "gene_OR13H1",
    "gene_FRMD7",
    "gene_HS6ST2",
    "gene_USP26",
    "gene_TFDP3",
    "gene_PLAC1",
    "gene_INTS6L",
    "gene_CXorf66",
    "gene_SOX3",
    "gene_CDR1",
    "gene_SPANXB1",
    "gene_SPANXD",
    "gene_MAGEC3",
    "gene_MAGEC1",
    "gene_SPANXN4",
    "gene_SPANXN3",
    "gene_SPANXN2",
    "gene_IDS",
    "gene_HSFX3",
    "gene_MAGEA9B",
    "gene_MAGEA11",
    "gene_MAGEA8",
    "gene_HMGB3",
    "gene_PASD1",
    "gene_CNGA2",
    "gene_MAGEA10",
    "gene_CSAG1",
    "gene_MAGEA12",
    "gene_MAGEA6",
    "gene_CETN2",
    "gene_MAGEA1",
    "gene_AC236972.4",
    "gene_PNMA6E",
    "gene_BGN",
    "gene_CCNQ",
    "gene_AVPR2",
    "gene_OPN1LW",
    "gene_TKTL1",
    "gene_FLNA",
    "gene_TBL1Y",
    "gene_MT-ND2",
    "gene_MT-CO2"
  ]
}